<?xml version='1.0' encoding='utf-8'?>
<metadata><image>kh_data_953.png</image><width>605</width><height>390</height><word><text>អស់</text><bbox><x1>10</x1><y1>10</y1><x2>47</x2><y2>34</y2></bbox></word><word><text>រយៈពេល</text><bbox><x1>47</x1><y1>10</y1><x2>130</x2><y2>34</y2></bbox></word><word><text>រាប់</text><bbox><x1>130</x1><y1>10</y1><x2>160</x2><y2>34</y2></bbox></word><word><text>សតវត្សរ៍</text><bbox><x1>160</x1><y1>10</y1><x2>247</x2><y2>41</y2></bbox></word><word><text> </text><bbox><x1>247</x1><y1>10</y1><x2>253</x2><y2>33</y2></bbox></word><word><text>បណ្តា</text><bbox><x1>253</x1><y1>10</y1><x2>303</x2><y2>40</y2></bbox></word><word><text>ជន</text><bbox><x1>303</x1><y1>10</y1><x2>332</x2><y2>34</y2></bbox></word><word><text>ទូទៅ</text><bbox><x1>332</x1><y1>10</y1><x2>376</x2><y2>42</y2></bbox></word><word><text> </text><bbox><x1>376</x1><y1>10</y1><x2>382</x2><y2>33</y2></bbox></word><word><text>នៅលើ</text><bbox><x1>382</x1><y1>10</y1><x2>440</x2><y2>34</y2></bbox></word><word><text>ពិភពលោក</text><bbox><x1>440</x1><y1>10</y1><x2>537</x2><y2>34</y2></bbox></word><word><text>នាំគ្នា</text><bbox><x1>537</x1><y1>10</y1><x2>581</x2><y2>40</y2></bbox></word><word><text>ជឿ</text><bbox><x1>10</x1><y1>48</y1><x2>40</x2><y2>82</y2></bbox></word><word><text>ថា</text><bbox><x1>40</x1><y1>48</y1><x2>60</x2><y2>72</y2></bbox></word><word><text> </text><bbox><x1>60</x1><y1>48</y1><x2>66</x2><y2>71</y2></bbox></word><word><text>អ្នក</text><bbox><x1>66</x1><y1>48</y1><x2>98</x2><y2>78</y2></bbox></word><word><text>ដែល</text><bbox><x1>98</x1><y1>48</y1><x2>142</x2><y2>72</y2></bbox></word><word><text>បាន</text><bbox><x1>142</x1><y1>48</y1><x2>178</x2><y2>72</y2></bbox></word><word><text>រកឃើញ</text><bbox><x1>178</x1><y1>48</y1><x2>257</x2><y2>78</y2></bbox></word><word><text>ទ្វីប</text><bbox><x1>257</x1><y1>48</y1><x2>287</x2><y2>78</y2></bbox></word><word><text>អាមេរិក</text><bbox><x1>287</x1><y1>48</y1><x2>357</x2><y2>72</y2></bbox></word><word><text>មុន</text><bbox><x1>357</x1><y1>48</y1><x2>388</x2><y2>81</y2></bbox></word><word><text>គេ</text><bbox><x1>388</x1><y1>48</y1><x2>411</x2><y2>72</y2></bbox></word><word><text>បង្អស់</text><bbox><x1>411</x1><y1>48</y1><x2>462</x2><y2>78</y2></bbox></word><word><text> </text><bbox><x1>462</x1><y1>48</y1><x2>468</x2><y2>71</y2></bbox></word><word><text>គឺ</text><bbox><x1>468</x1><y1>48</y1><x2>484</x2><y2>72</y2></bbox></word><word><text> </text><bbox><x1>484</x1><y1>48</y1><x2>490</x2><y2>71</y2></bbox></word><word><text>គ្រីស្តូហ្វ</text><bbox><x1>490</x1><y1>48</y1><x2>556</x2><y2>84</y2></bbox></word><word><text> </text><bbox><x1>556</x1><y1>48</y1><x2>562</x2><y2>71</y2></bbox></word><word><text>កូឡុំ</text><bbox><x1>562</x1><y1>48</y1><x2>602</x2><y2>86</y2></bbox></word><word><text> </text><bbox><x1>10</x1><y1>86</y1><x2>16</x2><y2>109</y2></bbox></word><word><text>(Christophe</text><bbox><x1>16</x1><y1>86</y1><x2>119</x2><y2>113</y2></bbox></word><word><text> </text><bbox><x1>119</x1><y1>86</y1><x2>125</x2><y2>109</y2></bbox></word><word><text>Colomb)</text><bbox><x1>125</x1><y1>86</y1><x2>199</x2><y2>113</y2></bbox></word><word><text>។</text><bbox><x1>199</x1><y1>86</y1><x2>213</x2><y2>110</y2></bbox></word><word><text> </text><bbox><x1>213</x1><y1>86</y1><x2>219</x2><y2>109</y2></bbox></word><word><text>ដំណើរ</text><bbox><x1>219</x1><y1>86</y1><x2>277</x2><y2>110</y2></bbox></word><word><text>រឿង</text><bbox><x1>277</x1><y1>86</y1><x2>316</x2><y2>120</y2></bbox></word><word><text>របស់</text><bbox><x1>316</x1><y1>86</y1><x2>361</x2><y2>110</y2></bbox></word><word><text> </text><bbox><x1>361</x1><y1>86</y1><x2>367</x2><y2>109</y2></bbox></word><word><text>គ្រីស្តូហ្វ</text><bbox><x1>367</x1><y1>86</y1><x2>433</x2><y2>122</y2></bbox></word><word><text> </text><bbox><x1>433</x1><y1>86</y1><x2>439</x2><y2>109</y2></bbox></word><word><text>កូឡុំ</text><bbox><x1>439</x1><y1>86</y1><x2>479</x2><y2>124</y2></bbox></word><word><text> </text><bbox><x1>479</x1><y1>86</y1><x2>485</x2><y2>109</y2></bbox></word><word><text>បាន</text><bbox><x1>485</x1><y1>86</y1><x2>521</x2><y2>110</y2></bbox></word><word><text>កើតឡើង</text><bbox><x1>10</x1><y1>124</y1><x2>96</x2><y2>154</y2></bbox></word><word><text> </text><bbox><x1>96</x1><y1>124</y1><x2>102</x2><y2>147</y2></bbox></word><word><text>នៅ</text><bbox><x1>102</x1><y1>124</y1><x2>132</x2><y2>148</y2></bbox></word><word><text>ចុង</text><bbox><x1>132</x1><y1>124</y1><x2>162</x2><y2>157</y2></bbox></word><word><text>សតវត្សរ៍</text><bbox><x1>162</x1><y1>124</y1><x2>249</x2><y2>155</y2></bbox></word><word><text>ទី</text><bbox><x1>249</x1><y1>124</y1><x2>264</x2><y2>148</y2></bbox></word><word><text>១៥</text><bbox><x1>264</x1><y1>124</y1><x2>295</x2><y2>148</y2></bbox></word><word><text>។</text><bbox><x1>295</x1><y1>124</y1><x2>309</x2><y2>148</y2></bbox></word><word><text> </text><bbox><x1>309</x1><y1>124</y1><x2>315</x2><y2>147</y2></bbox></word><word><text>នៅ</text><bbox><x1>315</x1><y1>124</y1><x2>345</x2><y2>148</y2></bbox></word><word><text>ពេល</text><bbox><x1>345</x1><y1>124</y1><x2>389</x2><y2>148</y2></bbox></word><word><text>នោះ</text><bbox><x1>389</x1><y1>124</y1><x2>427</x2><y2>148</y2></bbox></word><word><text> </text><bbox><x1>427</x1><y1>124</y1><x2>433</x2><y2>147</y2></bbox></word><word><text>អឺរ៉ុប</text><bbox><x1>433</x1><y1>124</y1><x2>473</x2><y2>157</y2></bbox></word><word><text>បាន</text><bbox><x1>473</x1><y1>124</y1><x2>509</x2><y2>148</y2></bbox></word><word><text>ងើប</text><bbox><x1>509</x1><y1>124</y1><x2>547</x2><y2>148</y2></bbox></word><word><text>ចេញ</text><bbox><x1>547</x1><y1>124</y1><x2>593</x2><y2>154</y2></bbox></word><word><text>ពី</text><bbox><x1>10</x1><y1>162</y1><x2>25</x2><y2>186</y2></bbox></word><word><text>យុគ</text><bbox><x1>25</x1><y1>162</y1><x2>64</x2><y2>195</y2></bbox></word><word><text>ខ្មៅ</text><bbox><x1>64</x1><y1>162</y1><x2>95</x2><y2>192</y2></bbox></word><word><text>ងងឹត</text><bbox><x1>95</x1><y1>162</y1><x2>141</x2><y2>185</y2></bbox></word><word><text> </text><bbox><x1>141</x1><y1>162</y1><x2>147</x2><y2>185</y2></bbox></word><word><text>នៃ</text><bbox><x1>147</x1><y1>162</y1><x2>170</x2><y2>186</y2></bbox></word><word><text>យុគសម័យ</text><bbox><x1>170</x1><y1>162</y1><x2>270</x2><y2>195</y2></bbox></word><word><text>កណ្តាល</text><bbox><x1>270</x1><y1>162</y1><x2>342</x2><y2>192</y2></bbox></word><word><text> </text><bbox><x1>342</x1><y1>162</y1><x2>348</x2><y2>185</y2></bbox></word><word><text>ហើយ</text><bbox><x1>348</x1><y1>162</y1><x2>400</x2><y2>186</y2></bbox></word><word><text>ចាប់ផ្តើម</text><bbox><x1>400</x1><y1>162</y1><x2>475</x2><y2>192</y2></bbox></word><word><text>ស្គាល់</text><bbox><x1>475</x1><y1>162</y1><x2>523</x2><y2>192</y2></bbox></word><word><text>នូវ</text><bbox><x1>523</x1><y1>162</y1><x2>553</x2><y2>194</y2></bbox></word><word><text>ភាពរុងរឿង</text><bbox><x1>10</x1><y1>200</y1><x2>109</x2><y2>234</y2></bbox></word><word><text>ឡើងវិញ</text><bbox><x1>109</x1><y1>200</y1><x2>193</x2><y2>230</y2></bbox></word><word><text>បន្តិច</text><bbox><x1>193</x1><y1>200</y1><x2>239</x2><y2>230</y2></bbox></word><word><text>ម្តង</text><bbox><x1>239</x1><y1>200</y1><x2>269</x2><y2>230</y2></bbox></word><word><text>ៗ</text><bbox><x1>269</x1><y1>200</y1><x2>283</x2><y2>228</y2></bbox></word><word><text> </text><bbox><x1>283</x1><y1>200</y1><x2>289</x2><y2>223</y2></bbox></word><word><text>ហើយ</text><bbox><x1>289</x1><y1>200</y1><x2>341</x2><y2>224</y2></bbox></word><word><text>ក្នុង</text><bbox><x1>341</x1><y1>200</y1><x2>372</x2><y2>236</y2></bbox></word><word><text>នោះ</text><bbox><x1>372</x1><y1>200</y1><x2>410</x2><y2>224</y2></bbox></word><word><text> </text><bbox><x1>410</x1><y1>200</y1><x2>416</x2><y2>223</y2></bbox></word><word><text>គឺ</text><bbox><x1>416</x1><y1>200</y1><x2>432</x2><y2>224</y2></bbox></word><word><text>ឃើញ</text><bbox><x1>432</x1><y1>200</y1><x2>486</x2><y2>230</y2></bbox></word><word><text>មាន</text><bbox><x1>486</x1><y1>200</y1><x2>523</x2><y2>224</y2></bbox></word><word><text>ប្រទេស</text><bbox><x1>523</x1><y1>200</y1><x2>590</x2><y2>231</y2></bbox></word><word><text>មហា</text><bbox><x1>10</x1><y1>238</y1><x2>53</x2><y2>261</y2></bbox></word><word><text>អំណាច</text><bbox><x1>53</x1><y1>238</y1><x2>120</x2><y2>262</y2></bbox></word><word><text>ថ្មី</text><bbox><x1>120</x1><y1>238</y1><x2>135</x2><y2>268</y2></bbox></word><word><text> </text><bbox><x1>135</x1><y1>238</y1><x2>141</x2><y2>261</y2></bbox></word><word><text>ដែល</text><bbox><x1>141</x1><y1>238</y1><x2>185</x2><y2>262</y2></bbox></word><word><text>ចាប់ផ្តើម</text><bbox><x1>185</x1><y1>238</y1><x2>260</x2><y2>268</y2></bbox></word><word><text>លេច</text><bbox><x1>260</x1><y1>238</y1><x2>304</x2><y2>262</y2></bbox></word><word><text>មុខ</text><bbox><x1>304</x1><y1>238</y1><x2>334</x2><y2>271</y2></bbox></word><word><text>ឡើង</text><bbox><x1>334</x1><y1>238</y1><x2>380</x2><y2>268</y2></bbox></word><word><text> </text><bbox><x1>380</x1><y1>238</y1><x2>386</x2><y2>261</y2></bbox></word><word><text>នៅ</text><bbox><x1>386</x1><y1>238</y1><x2>416</x2><y2>262</y2></bbox></word></metadata>