<?xml version='1.0' encoding='utf-8'?>
<metadata><image>kh_data_2037.png</image><width>420</width><height>390</height><word><text>កូនស្រី</text><bbox><x1>10</x1><y1>10</y1><x2>66</x2><y2>42</y2></bbox></word><word><text>ឈ្មោះ</text><bbox><x1>66</x1><y1>10</y1><x2>117</x2><y2>42</y2></bbox></word><word><text>នាង</text><bbox><x1>117</x1><y1>10</y1><x2>152</x2><y2>35</y2></bbox></word><word><text>សួស្ដី</text><bbox><x1>152</x1><y1>10</y1><x2>194</x2><y2>42</y2></bbox></word><word><text>មក</text><bbox><x1>194</x1><y1>10</y1><x2>223</x2><y2>35</y2></bbox></word><word><text>ផ្ទឹម</text><bbox><x1>223</x1><y1>10</y1><x2>252</x2><y2>42</y2></bbox></word><word><text>នឹង</text><bbox><x1>252</x1><y1>10</y1><x2>280</x2><y2>35</y2></bbox></word><word><text>ធន</text><bbox><x1>280</x1><y1>10</y1><x2>308</x2><y2>35</y2></bbox></word><word><text>ញ្ជ័យ</text><bbox><x1>308</x1><y1>10</y1><x2>350</x2><y2>42</y2></bbox></word><word><text> </text><bbox><x1>350</x1><y1>10</y1><x2>356</x2><y2>35</y2></bbox></word><word><text>ហើយ</text><bbox><x1>356</x1><y1>10</y1><x2>405</x2><y2>35</y2></bbox></word><word><text>រាង</text><bbox><x1>10</x1><y1>47</y1><x2>38</x2><y2>72</y2></bbox></word><word><text>បើក</text><bbox><x1>38</x1><y1>47</y1><x2>74</x2><y2>72</y2></bbox></word><word><text>បាយ</text><bbox><x1>74</x1><y1>47</y1><x2>116</x2><y2>74</y2></bbox></word><word><text>ខុន</text><bbox><x1>116</x1><y1>47</y1><x2>144</x2><y2>79</y2></bbox></word><word><text>ចង</text><bbox><x1>144</x1><y1>47</y1><x2>172</x2><y2>72</y2></bbox></word><word><text>ដែ</text><bbox><x1>172</x1><y1>47</y1><x2>193</x2><y2>72</y2></bbox></word><word><text>រួចហើយ</text><bbox><x1>193</x1><y1>47</y1><x2>264</x2><y2>79</y2></bbox></word><word><text> </text><bbox><x1>264</x1><y1>47</y1><x2>270</x2><y2>72</y2></bbox></word><word><text>ដល់</text><bbox><x1>270</x1><y1>47</y1><x2>305</x2><y2>72</y2></bbox></word><word><text>យប់</text><bbox><x1>305</x1><y1>47</y1><x2>341</x2><y2>72</y2></bbox></word><word><text>ផ្សំ</text><bbox><x1>341</x1><y1>47</y1><x2>362</x2><y2>79</y2></bbox></word><word><text>ដំណេក</text><bbox><x1>10</x1><y1>84</y1><x2>73</x2><y2>109</y2></bbox></word><word><text> </text><bbox><x1>73</x1><y1>84</y1><x2>79</x2><y2>109</y2></bbox></word><word><text>អ្នក</text><bbox><x1>79</x1><y1>84</y1><x2>108</x2><y2>116</y2></bbox></word><word><text>ជ័យ</text><bbox><x1>108</x1><y1>84</y1><x2>143</x2><y2>109</y2></bbox></word><word><text> </text><bbox><x1>143</x1><y1>84</y1><x2>149</x2><y2>109</y2></bbox></word><word><text>និង</text><bbox><x1>149</x1><y1>84</y1><x2>177</x2><y2>109</y2></bbox></word><word><text>នាង</text><bbox><x1>177</x1><y1>84</y1><x2>212</x2><y2>109</y2></bbox></word><word><text>សួស្ដី</text><bbox><x1>212</x1><y1>84</y1><x2>254</x2><y2>116</y2></bbox></word><word><text>ជា</text><bbox><x1>254</x1><y1>84</y1><x2>275</x2><y2>109</y2></bbox></word><word><text>ប្ដី</text><bbox><x1>275</x1><y1>84</y1><x2>289</x2><y2>116</y2></bbox></word><word><text>ប្រពន្ធ</text><bbox><x1>289</x1><y1>84</y1><x2>339</x2><y2>116</y2></bbox></word><word><text> </text><bbox><x1>339</x1><y1>84</y1><x2>345</x2><y2>109</y2></bbox></word><word><text>រួច</text><bbox><x1>345</x1><y1>84</y1><x2>367</x2><y2>116</y2></bbox></word><word><text>ការវល់</text><bbox><x1>10</x1><y1>121</y1><x2>66</x2><y2>146</y2></bbox></word><word><text>ពី</text><bbox><x1>66</x1><y1>121</y1><x2>80</x2><y2>146</y2></bbox></word><word><text>ថ្ងៃ</text><bbox><x1>80</x1><y1>121</y1><x2>101</x2><y2>153</y2></bbox></word><word><text>នេះ</text><bbox><x1>101</x1><y1>121</y1><x2>131</x2><y2>146</y2></bbox></word><word><text>ទៅ</text><bbox><x1>131</x1><y1>121</y1><x2>159</x2><y2>146</y2></bbox></word><word><text>ហើយ</text><bbox><x1>159</x1><y1>121</y1><x2>208</x2><y2>146</y2></bbox></word><word><text>ទើប</text><bbox><x1>208</x1><y1>121</y1><x2>244</x2><y2>146</y2></bbox></word><word><text>ធន</text><bbox><x1>244</x1><y1>121</y1><x2>272</x2><y2>146</y2></bbox></word><word><text>ញ្ជ័យ</text><bbox><x1>272</x1><y1>121</y1><x2>314</x2><y2>153</y2></bbox></word><word><text>និយាយ</text><bbox><x1>314</x1><y1>121</y1><x2>377</x2><y2>146</y2></bbox></word><word><text>នឹង</text><bbox><x1>377</x1><y1>121</y1><x2>405</x2><y2>146</y2></bbox></word><word><text>ឪពុក</text><bbox><x1>10</x1><y1>158</y1><x2>52</x2><y2>190</y2></bbox></word><word><text>ក្មេក</text><bbox><x1>52</x1><y1>158</y1><x2>87</x2><y2>190</y2></bbox></word><word><text> </text><bbox><x1>87</x1><y1>158</y1><x2>93</x2><y2>183</y2></bbox></word><word><text>និង</text><bbox><x1>93</x1><y1>158</y1><x2>121</x2><y2>183</y2></bbox></word><word><text>ប្រពន្ធ</text><bbox><x1>121</x1><y1>158</y1><x2>171</x2><y2>190</y2></bbox></word><word><text>ថា</text><bbox><x1>171</x1><y1>158</y1><x2>192</x2><y2>183</y2></bbox></word><word><text> </text><bbox><x1>192</x1><y1>158</y1><x2>198</x2><y2>183</y2></bbox></word><word><text>នឹង</text><bbox><x1>198</x1><y1>158</y1><x2>226</x2><y2>183</y2></bbox></word><word><text>ទៅ</text><bbox><x1>226</x1><y1>158</y1><x2>254</x2><y2>183</y2></bbox></word><word><text>ទារ</text><bbox><x1>254</x1><y1>158</y1><x2>282</x2><y2>183</y2></bbox></word><word><text>ប្រាក់</text><bbox><x1>282</x1><y1>158</y1><x2>324</x2><y2>189</y2></bbox></word><word><text>ដែល</text><bbox><x1>324</x1><y1>158</y1><x2>366</x2><y2>183</y2></bbox></word><word><text>អស់</text><bbox><x1>366</x1><y1>158</y1><x2>402</x2><y2>183</y2></bbox></word><word><text>នា</text><bbox><x1>10</x1><y1>195</y1><x2>31</x2><y2>220</y2></bbox></word><word><text>ម៉ឺន</text><bbox><x1>31</x1><y1>195</y1><x2>60</x2><y2>227</y2></bbox></word><word><text>ជម្ពាក់</text><bbox><x1>60</x1><y1>195</y1><x2>110</x2><y2>227</y2></bbox></word><word><text>។</text><bbox><x1>110</x1><y1>195</y1><x2>125</x2><y2>220</y2></bbox></word><word><text> </text><bbox><x1>125</x1><y1>195</y1><x2>131</x2><y2>220</y2></bbox></word><word><text>ធន</text><bbox><x1>131</x1><y1>195</y1><x2>159</x2><y2>220</y2></bbox></word><word><text>ញ្ជ័យ</text><bbox><x1>159</x1><y1>195</y1><x2>201</x2><y2>227</y2></bbox></word><word><text>ទៅដល់</text><bbox><x1>201</x1><y1>195</y1><x2>264</x2><y2>220</y2></bbox></word><word><text>សាលា</text><bbox><x1>264</x1><y1>195</y1><x2>320</x2><y2>220</y2></bbox></word><word><text>ជំនុំ</text><bbox><x1>320</x1><y1>195</y1><x2>348</x2><y2>227</y2></bbox></word><word><text>អស់</text><bbox><x1>348</x1><y1>195</y1><x2>384</x2><y2>220</y2></bbox></word><word><text>នា</text><bbox><x1>384</x1><y1>195</y1><x2>405</x2><y2>220</y2></bbox></word><word><text>ម៉ឺន</text><bbox><x1>10</x1><y1>232</y1><x2>39</x2><y2>264</y2></bbox></word><word><text>ធំ</text><bbox><x1>39</x1><y1>232</y1><x2>53</x2><y2>257</y2></bbox></word><word><text> </text><bbox><x1>53</x1><y1>232</y1><x2>59</x2><y2>257</y2></bbox></word><word><text>តូច</text><bbox><x1>59</x1><y1>232</y1><x2>87</x2><y2>264</y2></bbox></word><word><text>ច្រើន</text><bbox><x1>87</x1><y1>232</y1><x2>129</x2><y2>263</y2></bbox></word><word><text> </text><bbox><x1>129</x1><y1>232</y1><x2>135</x2><y2>257</y2></bbox></word><word><text>ក៏</text><bbox><x1>135</x1><y1>232</y1><x2>149</x2><y2>257</y2></bbox></word><word><text>ឡើង</text><bbox><x1>149</x1><y1>232</y1><x2>191</x2><y2>264</y2></bbox></word><word><text>ទៅ</text><bbox><x1>191</x1><y1>232</y1><x2>219</x2><y2>257</y2></bbox></word><word><text>លើ</text><bbox><x1>219</x1><y1>232</y1><x2>247</x2><y2>257</y2></bbox></word><word><text>សាលា</text><bbox><x1>247</x1><y1>232</y1><x2>303</x2><y2>257</y2></bbox></word><word><text> </text><bbox><x1>303</x1><y1>232</y1><x2>309</x2><y2>257</y2></bbox></word><word><text>ហើយនិយាយ</text><bbox><x1>10</x1><y1>269</y1><x2>122</x2><y2>294</y2></bbox></word><word><text>នឹង</text><bbox><x1>122</x1><y1>269</y1><x2>150</x2><y2>294</y2></bbox></word><word><text>អស់</text><bbox><x1>150</x1><y1>269</y1><x2>186</x2><y2>294</y2></bbox></word><word><text>នា</text><bbox><x1>186</x1><y1>269</y1><x2>207</x2><y2>294</y2></bbox></word><word><text>ម៉ឺន</text><bbox><x1>207</x1><y1>269</y1><x2>236</x2><y2>301</y2></bbox></word><word><text>ថា</text><bbox><x1>236</x1><y1>269</y1><x2>257</x2><y2>294</y2></bbox></word><word><text> </text><bbox><x1>257</x1><y1>269</y1><x2>263</x2><y2>294</y2></bbox></word><word><text>បើ</text><bbox><x1>263</x1><y1>269</y1><x2>284</x2><y2>294</y2></bbox></word><word><text>ចង់</text><bbox><x1>284</x1><y1>269</y1><x2>312</x2><y2>294</y2></bbox></word><word><text>ភ្នាល់</text><bbox><x1>312</x1><y1>269</y1><x2>354</x2><y2>301</y2></bbox></word><word><text>នឹង</text><bbox><x1>354</x1><y1>269</y1><x2>382</x2><y2>294</y2></bbox></word><word><text>ខ្ញុំ</text><bbox><x1>382</x1><y1>269</y1><x2>396</x2><y2>306</y2></bbox></word><word><text>ៗ</text><bbox><x1>396</x1><y1>269</y1><x2>411</x2><y2>294</y2></bbox></word><word><text>នឹង</text><bbox><x1>10</x1><y1>306</y1><x2>38</x2><y2>331</y2></bbox></word><word><text>ប្រើ</text><bbox><x1>38</x1><y1>306</y1><x2>66</x2><y2>337</y2></bbox></word><word><text>ស្ដេច</text><bbox><x1>66</x1><y1>306</y1><x2>108</x2><y2>338</y2></bbox></word><word><text>ឱ្យ</text><bbox><x1>108</x1><y1>306</y1><x2>129</x2><y2>338</y2></bbox></word></metadata>