<?xml version='1.0' encoding='utf-8'?>
<metadata><image>kh_data_760.png</image><width>566</width><height>380</height><word><text>ស្រាល</text><bbox><x1>10</x1><y1>10</y1><x2>66</x2><y2>41</y2></bbox></word><word><text>សមត្ថភាព</text><bbox><x1>66</x1><y1>10</y1><x2>151</x2><y2>42</y2></bbox></word><word><text>មនុស្ស</text><bbox><x1>151</x1><y1>10</y1><x2>208</x2><y2>42</y2></bbox></word><word><text>ចាស់</text><bbox><x1>208</x1><y1>10</y1><x2>250</x2><y2>35</y2></bbox></word><word><text>វិញ</text><bbox><x1>250</x1><y1>10</y1><x2>280</x2><y2>41</y2></bbox></word><word><text>។</text><bbox><x1>280</x1><y1>10</y1><x2>295</x2><y2>35</y2></bbox></word><word><text> </text><bbox><x1>295</x1><y1>10</y1><x2>301</x2><y2>35</y2></bbox></word><word><text>ការ</text><bbox><x1>301</x1><y1>10</y1><x2>329</x2><y2>35</y2></bbox></word><word><text>មិន</text><bbox><x1>329</x1><y1>10</y1><x2>358</x2><y2>35</y2></bbox></word><word><text>ចុះសម្រុង</text><bbox><x1>358</x1><y1>10</y1><x2>438</x2><y2>42</y2></bbox></word><word><text>គ្នា</text><bbox><x1>438</x1><y1>10</y1><x2>459</x2><y2>42</y2></bbox></word><word><text>នេះ</text><bbox><x1>459</x1><y1>10</y1><x2>489</x2><y2>35</y2></bbox></word><word><text>បាន</text><bbox><x1>489</x1><y1>10</y1><x2>524</x2><y2>37</y2></bbox></word><word><text>និង</text><bbox><x1>524</x1><y1>10</y1><x2>552</x2><y2>35</y2></bbox></word><word><text>កំពុង</text><bbox><x1>10</x1><y1>47</y1><x2>52</x2><y2>79</y2></bbox></word><word><text>បង្កឱ្យ</text><bbox><x1>52</x1><y1>47</y1><x2>102</x2><y2>79</y2></bbox></word><word><text>មាន</text><bbox><x1>102</x1><y1>47</y1><x2>138</x2><y2>72</y2></bbox></word><word><text>គម្លាត</text><bbox><x1>138</x1><y1>47</y1><x2>188</x2><y2>79</y2></bbox></word><word><text>ដាច់</text><bbox><x1>188</x1><y1>47</y1><x2>223</x2><y2>72</y2></bbox></word><word><text>ពី</text><bbox><x1>223</x1><y1>47</y1><x2>237</x2><y2>72</y2></bbox></word><word><text>គ្នា</text><bbox><x1>237</x1><y1>47</y1><x2>258</x2><y2>79</y2></bbox></word><word><text>កាន់តែ</text><bbox><x1>258</x1><y1>47</y1><x2>314</x2><y2>72</y2></bbox></word><word><text>ឆ្ងាយ</text><bbox><x1>314</x1><y1>47</y1><x2>356</x2><y2>79</y2></bbox></word><word><text>រវាង</text><bbox><x1>356</x1><y1>47</y1><x2>391</x2><y2>72</y2></bbox></word><word><text>ជំនាន់</text><bbox><x1>391</x1><y1>47</y1><x2>440</x2><y2>72</y2></bbox></word><word><text>មនុស្ស</text><bbox><x1>440</x1><y1>47</y1><x2>497</x2><y2>79</y2></bbox></word><word><text>មួយ</text><bbox><x1>497</x1><y1>47</y1><x2>533</x2><y2>79</y2></bbox></word><word><text>ទៅ</text><bbox><x1>533</x1><y1>47</y1><x2>561</x2><y2>72</y2></bbox></word><word><text>មនុស្ស</text><bbox><x1>10</x1><y1>84</y1><x2>67</x2><y2>116</y2></bbox></word><word><text>មួយ</text><bbox><x1>67</x1><y1>84</y1><x2>103</x2><y2>116</y2></bbox></word><word><text>ទៀត</text><bbox><x1>103</x1><y1>84</y1><x2>145</x2><y2>116</y2></bbox></word><word><text> </text><bbox><x1>145</x1><y1>84</y1><x2>151</x2><y2>109</y2></bbox></word><word><text>ដែល</text><bbox><x1>151</x1><y1>84</y1><x2>193</x2><y2>109</y2></bbox></word><word><text>ពិបាក</text><bbox><x1>193</x1><y1>84</y1><x2>242</x2><y2>111</y2></bbox></word><word><text>នឹង</text><bbox><x1>242</x1><y1>84</y1><x2>270</x2><y2>109</y2></bbox></word><word><text>តភ្ជាប់គ្នា</text><bbox><x1>270</x1><y1>84</y1><x2>341</x2><y2>116</y2></bbox></word><word><text> </text><bbox><x1>341</x1><y1>84</y1><x2>347</x2><y2>109</y2></bbox></word><word><text>នៅ</text><bbox><x1>347</x1><y1>84</y1><x2>375</x2><y2>109</y2></bbox></word><word><text>កន្លែង</text><bbox><x1>375</x1><y1>84</y1><x2>424</x2><y2>116</y2></bbox></word><word><text>ធ្វើការ</text><bbox><x1>424</x1><y1>84</y1><x2>473</x2><y2>116</y2></bbox></word><word><text> </text><bbox><x1>473</x1><y1>84</y1><x2>479</x2><y2>109</y2></bbox></word><word><text>មនុស្ស</text><bbox><x1>479</x1><y1>84</y1><x2>536</x2><y2>116</y2></bbox></word><word><text>ចាស់</text><bbox><x1>10</x1><y1>121</y1><x2>52</x2><y2>146</y2></bbox></word><word><text>ហាក់</text><bbox><x1>52</x1><y1>121</y1><x2>94</x2><y2>146</y2></bbox></word><word><text>ព្រួយបារម្ភ</text><bbox><x1>94</x1><y1>121</y1><x2>179</x2><y2>153</y2></bbox></word><word><text>អំពី</text><bbox><x1>179</x1><y1>121</y1><x2>208</x2><y2>146</y2></bbox></word><word><text>មហិច្ឆតា</text><bbox><x1>208</x1><y1>121</y1><x2>279</x2><y2>153</y2></bbox></word><word><text>ចង់</text><bbox><x1>279</x1><y1>121</y1><x2>307</x2><y2>146</y2></bbox></word><word><text>ដណ្តើម</text><bbox><x1>307</x1><y1>121</y1><x2>370</x2><y2>153</y2></bbox></word><word><text>កៅអី</text><bbox><x1>370</x1><y1>121</y1><x2>412</x2><y2>146</y2></bbox></word><word><text>របស់់</text><bbox><x1>412</x1><y1>121</y1><x2>454</x2><y2>146</y2></bbox></word><word><text>ខ្លួន</text><bbox><x1>454</x1><y1>121</y1><x2>482</x2><y2>158</y2></bbox></word><word><text>ពីសំណាក់</text><bbox><x1>482</x1><y1>121</y1><x2>566</x2><y2>146</y2></bbox></word><word><text>ក្មេង</text><bbox><x1>10</x1><y1>158</y1><x2>45</x2><y2>190</y2></bbox></word><word><text>ស្រករ</text><bbox><x1>45</x1><y1>158</y1><x2>94</x2><y2>189</y2></bbox></word><word><text>ក្រោយ</text><bbox><x1>94</x1><y1>158</y1><x2>150</x2><y2>189</y2></bbox></word><word><text>ខណៈ</text><bbox><x1>150</x1><y1>158</y1><x2>200</x2><y2>183</y2></bbox></word><word><text>ដែល</text><bbox><x1>200</x1><y1>158</y1><x2>242</x2><y2>183</y2></bbox></word><word><text>យុវជន</text><bbox><x1>242</x1><y1>158</y1><x2>298</x2><y2>190</y2></bbox></word><word><text>ខ្លះ</text><bbox><x1>298</x1><y1>158</y1><x2>321</x2><y2>190</y2></bbox></word><word><text>វិញ</text><bbox><x1>321</x1><y1>158</y1><x2>351</x2><y2>189</y2></bbox></word><word><text>មើល</text><bbox><x1>351</x1><y1>158</y1><x2>393</x2><y2>183</y2></bbox></word><word><text>ស្រាល</text><bbox><x1>393</x1><y1>158</y1><x2>449</x2><y2>189</y2></bbox></word><word><text>មនុស្ស</text><bbox><x1>449</x1><y1>158</y1><x2>506</x2><y2>190</y2></bbox></word><word><text>ចាស់</text><bbox><x1>506</x1><y1>158</y1><x2>548</x2><y2>183</y2></bbox></word><word><text> </text><bbox><x1>548</x1><y1>158</y1><x2>554</x2><y2>183</y2></bbox></word><word><text>ថា</text><bbox><x1>10</x1><y1>195</y1><x2>31</x2><y2>220</y2></bbox></word><word><text> </text><bbox><x1>31</x1><y1>195</y1><x2>37</x2><y2>220</y2></bbox></word><word><text>ធ្វើ</text><bbox><x1>37</x1><y1>195</y1><x2>58</x2><y2>227</y2></bbox></word><word><text>ការ</text><bbox><x1>58</x1><y1>195</y1><x2>86</x2><y2>220</y2></bbox></word><word><text>តាម</text><bbox><x1>86</x1><y1>195</y1><x2>122</x2><y2>220</y2></bbox></word><word><text>បែប</text><bbox><x1>122</x1><y1>195</y1><x2>158</x2><y2>220</y2></bbox></word><word><text>បុរាណ</text><bbox><x1>158</x1><y1>195</y1><x2>214</x2><y2>227</y2></bbox></word><word><text>ហួស</text><bbox><x1>214</x1><y1>195</y1><x2>256</x2><y2>227</y2></bbox></word><word><text>សម័យ</text><bbox><x1>256</x1><y1>195</y1><x2>313</x2><y2>220</y2></bbox></word><word><text> </text><bbox><x1>313</x1><y1>195</y1><x2>319</x2><y2>220</y2></bbox></word><word><text>ហើយ</text><bbox><x1>319</x1><y1>195</y1><x2>368</x2><y2>220</y2></bbox></word><word><text>មិន</text><bbox><x1>368</x1><y1>195</y1><x2>397</x2><y2>220</y2></bbox></word><word><text>ព្រម</text><bbox><x1>397</x1><y1>195</y1><x2>433</x2><y2>226</y2></bbox></word><word><text>ទទួលស្គាល់</text><bbox><x1>433</x1><y1>195</y1><x2>532</x2><y2>227</y2></bbox></word><word><text>សមត្ថភាព</text><bbox><x1>10</x1><y1>232</y1><x2>95</x2><y2>264</y2></bbox></word><word><text>ក្មេង</text><bbox><x1>95</x1><y1>232</y1><x2>130</x2><y2>264</y2></bbox></word><word><text>ជំនាន់</text><bbox><x1>130</x1><y1>232</y1><x2>179</x2><y2>257</y2></bbox></word><word><text>ក្រោយ</text><bbox><x1>179</x1><y1>232</y1><x2>235</x2><y2>263</y2></bbox></word><word><text>ព្រោះ</text><bbox><x1>235</x1><y1>232</y1><x2>279</x2><y2>263</y2></bbox></word><word><text>ខ្លាច</text><bbox><x1>279</x1><y1>232</y1><x2>314</x2><y2>264</y2></bbox></word><word><text>អន់</text><bbox><x1>314</x1><y1>232</y1><x2>343</x2><y2>257</y2></bbox></word><word><text>។</text><bbox><x1>343</x1><y1>232</y1><x2>358</x2><y2>257</y2></bbox></word><word><text> </text><bbox><x1>358</x1><y1>232</y1><x2>364</x2><y2>257</y2></bbox></word><word><text>ម៉្យាងទៀត</text><bbox><x1>364</x1><y1>232</y1><x2>448</x2><y2>264</y2></bbox></word><word><text>មនុស្ស</text><bbox><x1>448</x1><y1>232</y1><x2>505</x2><y2>264</y2></bbox></word><word><text>ចាស់</text><bbox><x1>505</x1><y1>232</y1><x2>547</x2><y2>257</y2></bbox></word><word><text>ខ្លះ</text><bbox><x1>10</x1><y1>269</y1><x2>33</x2><y2>301</y2></bbox></word><word><text> </text><bbox><x1>33</x1><y1>269</y1><x2>39</x2><y2>294</y2></bbox></word><word><text>ក្រាញ</text><bbox><x1>39</x1><y1>269</y1><x2>88</x2><y2>300</y2></bbox></word><word><text>ននៀល</text><bbox><x1>88</x1><y1>269</y1><x2>151</x2><y2>301</y2></bbox></word><word><text>និង</text><bbox><x1>151</x1><y1>269</y1><x2>179</x2><y2>294</y2></bbox></word><word><text>តួនាទី</text><bbox><x1>179</x1><y1>269</y1><x2>228</x2><y2>301</y2></bbox></word><word><text>មិន</text><bbox><x1>228</x1><y1>269</y1><x2>257</x2><y2>294</y2></bbox></word><word><text>ព្រម</text><bbox><x1>257</x1><y1>269</y1><x2>293</x2><y2>300</y2></bbox></word></metadata>