<?xml version='1.0' encoding='utf-8'?>
<metadata><image>kh_data_3027.png</image><width>515</width><height>390</height><word><text>ទៀត</text><bbox><x1>10</x1><y1>10</y1><x2>52</x2><y2>42</y2></bbox></word><word><text>ឆ្លៀត</text><bbox><x1>52</x1><y1>10</y1><x2>94</x2><y2>47</y2></bbox></word><word><text>រត់</text><bbox><x1>94</x1><y1>10</y1><x2>115</x2><y2>35</y2></bbox></word><word><text>ម៉ូតូ</text><bbox><x1>115</x1><y1>10</y1><x2>144</x2><y2>42</y2></bbox></word><word><text>ឌុប</text><bbox><x1>144</x1><y1>10</y1><x2>173</x2><y2>42</y2></bbox></word><word><text> </text><bbox><x1>173</x1><y1>10</y1><x2>179</x2><y2>35</y2></bbox></word><word><text>ឬ</text><bbox><x1>179</x1><y1>10</y1><x2>193</x2><y2>41</y2></bbox></word><word><text>ប្រកបរបរ</text><bbox><x1>193</x1><y1>10</y1><x2>271</x2><y2>41</y2></bbox></word><word><text>កំប៉ិកកំប៉ុក</text><bbox><x1>271</x1><y1>10</y1><x2>356</x2><y2>42</y2></bbox></word><word><text>តាម</text><bbox><x1>356</x1><y1>10</y1><x2>392</x2><y2>35</y2></bbox></word><word><text>លទ្ធភាព</text><bbox><x1>392</x1><y1>10</y1><x2>463</x2><y2>42</y2></bbox></word><word><text>ដែល</text><bbox><x1>463</x1><y1>10</y1><x2>505</x2><y2>35</y2></bbox></word><word><text>អាច</text><bbox><x1>10</x1><y1>47</y1><x2>46</x2><y2>72</y2></bbox></word><word><text>ធ្វើ</text><bbox><x1>46</x1><y1>47</y1><x2>67</x2><y2>79</y2></bbox></word><word><text>ទៅ</text><bbox><x1>67</x1><y1>47</y1><x2>95</x2><y2>72</y2></bbox></word><word><text>បាន</text><bbox><x1>95</x1><y1>47</y1><x2>130</x2><y2>74</y2></bbox></word><word><text> </text><bbox><x1>130</x1><y1>47</y1><x2>136</x2><y2>72</y2></bbox></word><word><text>ដើម្បី</text><bbox><x1>136</x1><y1>47</y1><x2>179</x2><y2>79</y2></bbox></word><word><text>ដោះស្រាយ</text><bbox><x1>179</x1><y1>47</y1><x2>273</x2><y2>78</y2></bbox></word><word><text>ជីវភាព</text><bbox><x1>273</x1><y1>47</y1><x2>330</x2><y2>72</y2></bbox></word><word><text>ប្រចាំ</text><bbox><x1>330</x1><y1>47</y1><x2>372</x2><y2>78</y2></bbox></word><word><text>ថ្ងៃ</text><bbox><x1>372</x1><y1>47</y1><x2>393</x2><y2>79</y2></bbox></word><word><text>។</text><bbox><x1>393</x1><y1>47</y1><x2>408</x2><y2>72</y2></bbox></word><word><text> </text><bbox><x1>408</x1><y1>47</y1><x2>414</x2><y2>72</y2></bbox></word><word><text>បើ</text><bbox><x1>414</x1><y1>47</y1><x2>435</x2><y2>72</y2></bbox></word><word><text>ទោះបីជា</text><bbox><x1>435</x1><y1>47</y1><x2>508</x2><y2>72</y2></bbox></word><word><text>រស់</text><bbox><x1>10</x1><y1>84</y1><x2>38</x2><y2>109</y2></bbox></word><word><text>ក្នុង</text><bbox><x1>38</x1><y1>84</y1><x2>66</x2><y2>121</y2></bbox></word><word><text>ស្ថានភាព</text><bbox><x1>66</x1><y1>84</y1><x2>144</x2><y2>116</y2></bbox></word><word><text>លំបាក</text><bbox><x1>144</x1><y1>84</y1><x2>200</x2><y2>111</y2></bbox></word><word><text>លំបិន</text><bbox><x1>200</x1><y1>84</y1><x2>250</x2><y2>109</y2></bbox></word><word><text>យ៉ាងណា</text><bbox><x1>250</x1><y1>84</y1><x2>327</x2><y2>109</y2></bbox></word><word><text>ក៏ដោយ</text><bbox><x1>327</x1><y1>84</y1><x2>390</x2><y2>109</y2></bbox></word><word><text> </text><bbox><x1>390</x1><y1>84</y1><x2>396</x2><y2>109</y2></bbox></word><word><text>ក៏</text><bbox><x1>396</x1><y1>84</y1><x2>410</x2><y2>109</y2></bbox></word><word><text>លោកគ្រូ</text><bbox><x1>410</x1><y1>84</y1><x2>480</x2><y2>116</y2></bbox></word><word><text>អ្នកគ្រូ</text><bbox><x1>10</x1><y1>121</y1><x2>60</x2><y2>153</y2></bbox></word><word><text>នៅតែ</text><bbox><x1>60</x1><y1>121</y1><x2>109</x2><y2>146</y2></bbox></word><word><text>តស៊ូ</text><bbox><x1>109</x1><y1>121</y1><x2>144</x2><y2>153</y2></bbox></word><word><text> </text><bbox><x1>144</x1><y1>121</y1><x2>150</x2><y2>146</y2></bbox></word><word><text>អត់ធ្មត់</text><bbox><x1>150</x1><y1>121</y1><x2>207</x2><y2>153</y2></bbox></word><word><text>ដើម្បី</text><bbox><x1>207</x1><y1>121</y1><x2>250</x2><y2>153</y2></bbox></word><word><text>បំពេញ</text><bbox><x1>250</x1><y1>121</y1><x2>307</x2><y2>152</y2></bbox></word><word><text>ការងារ</text><bbox><x1>307</x1><y1>121</y1><x2>363</x2><y2>146</y2></bbox></word><word><text>របស់</text><bbox><x1>363</x1><y1>121</y1><x2>405</x2><y2>146</y2></bbox></word><word><text>ខ្លួន</text><bbox><x1>405</x1><y1>121</y1><x2>433</x2><y2>158</y2></bbox></word><word><text>ដោយ</text><bbox><x1>433</x1><y1>121</y1><x2>482</x2><y2>146</y2></bbox></word><word><text>ឥត</text><bbox><x1>482</x1><y1>121</y1><x2>510</x2><y2>146</y2></bbox></word><word><text>រួញរា</text><bbox><x1>10</x1><y1>158</y1><x2>53</x2><y2>190</y2></bbox></word><word><text>។</text><bbox><x1>53</x1><y1>158</y1><x2>68</x2><y2>183</y2></bbox></word><word><text> </text><bbox><x1>68</x1><y1>158</y1><x2>74</x2><y2>183</y2></bbox></word><word><text>ជា</text><bbox><x1>74</x1><y1>158</y1><x2>95</x2><y2>183</y2></bbox></word><word><text>លទ្ធផល</text><bbox><x1>95</x1><y1>158</y1><x2>166</x2><y2>190</y2></bbox></word><word><text> </text><bbox><x1>166</x1><y1>158</y1><x2>172</x2><y2>183</y2></bbox></word><word><text>សិស្ស</text><bbox><x1>172</x1><y1>158</y1><x2>221</x2><y2>190</y2></bbox></word><word><text> </text><bbox><x1>221</x1><y1>158</y1><x2>227</x2><y2>183</y2></bbox></word><word><text>និង</text><bbox><x1>227</x1><y1>158</y1><x2>255</x2><y2>183</y2></bbox></word><word><text>និស្សិត</text><bbox><x1>255</x1><y1>158</y1><x2>311</x2><y2>190</y2></bbox></word><word><text> </text><bbox><x1>311</x1><y1>158</y1><x2>317</x2><y2>183</y2></bbox></word><word><text>រាប់</text><bbox><x1>317</x1><y1>158</y1><x2>345</x2><y2>183</y2></bbox></word><word><text>សែន</text><bbox><x1>345</x1><y1>158</y1><x2>387</x2><y2>183</y2></bbox></word><word><text>នាក់</text><bbox><x1>387</x1><y1>158</y1><x2>422</x2><y2>183</y2></bbox></word><word><text>បាន</text><bbox><x1>422</x1><y1>158</y1><x2>457</x2><y2>185</y2></bbox></word><word><text>បញ្ចប់</text><bbox><x1>457</x1><y1>158</y1><x2>507</x2><y2>190</y2></bbox></word><word><text>ការសិក្សា</text><bbox><x1>10</x1><y1>195</y1><x2>87</x2><y2>227</y2></bbox></word><word><text>ជារៀងរាល់</text><bbox><x1>87</x1><y1>195</y1><x2>178</x2><y2>227</y2></bbox></word><word><text>ឆ្នាំ</text><bbox><x1>178</x1><y1>195</y1><x2>199</x2><y2>227</y2></bbox></word><word><text>។</text><bbox><x1>199</x1><y1>195</y1><x2>214</x2><y2>220</y2></bbox></word><word><text> </text><bbox><x1>214</x1><y1>195</y1><x2>220</x2><y2>220</y2></bbox></word><word><text>ជា</text><bbox><x1>220</x1><y1>195</y1><x2>241</x2><y2>220</y2></bbox></word><word><text>ការពិត</text><bbox><x1>241</x1><y1>195</y1><x2>297</x2><y2>220</y2></bbox></word><word><text>ណាស់</text><bbox><x1>297</x1><y1>195</y1><x2>353</x2><y2>220</y2></bbox></word><word><text> </text><bbox><x1>353</x1><y1>195</y1><x2>359</x2><y2>220</y2></bbox></word><word><text>បច្ចុប្បន្ន</text><bbox><x1>359</x1><y1>195</y1><x2>423</x2><y2>232</y2></bbox></word><word><text>នេះ</text><bbox><x1>423</x1><y1>195</y1><x2>453</x2><y2>220</y2></bbox></word><word><text> </text><bbox><x1>453</x1><y1>195</y1><x2>459</x2><y2>220</y2></bbox></word><word><text>គុណភាព</text><bbox><x1>10</x1><y1>232</y1><x2>87</x2><y2>264</y2></bbox></word><word><text>នៃ</text><bbox><x1>87</x1><y1>232</y1><x2>108</x2><y2>257</y2></bbox></word><word><text>ធនធាន</text><bbox><x1>108</x1><y1>232</y1><x2>172</x2><y2>257</y2></bbox></word><word><text>មនុស្ស</text><bbox><x1>172</x1><y1>232</y1><x2>229</x2><y2>264</y2></bbox></word><word><text>គឺជា</text><bbox><x1>229</x1><y1>232</y1><x2>264</x2><y2>257</y2></bbox></word><word><text>បញ្ហា</text><bbox><x1>264</x1><y1>232</y1><x2>306</x2><y2>264</y2></bbox></word><word><text>ស្លាប់</text><bbox><x1>306</x1><y1>232</y1><x2>348</x2><y2>264</y2></bbox></word><word><text>រស់</text><bbox><x1>348</x1><y1>232</y1><x2>376</x2><y2>257</y2></bbox></word><word><text>សម្រាប់</text><bbox><x1>376</x1><y1>232</y1><x2>440</x2><y2>263</y2></bbox></word><word><text>ប្រទេស</text><bbox><x1>440</x1><y1>232</y1><x2>504</x2><y2>263</y2></bbox></word><word><text>នីមួយ</text><bbox><x1>10</x1><y1>269</y1><x2>60</x2><y2>301</y2></bbox></word><word><text>។</text><bbox><x1>60</x1><y1>269</y1><x2>75</x2><y2>294</y2></bbox></word><word><text> </text><bbox><x1>75</x1><y1>269</y1><x2>81</x2><y2>294</y2></bbox></word><word><text>ដោយឡែក</text><bbox><x1>81</x1><y1>269</y1><x2>172</x2><y2>301</y2></bbox></word><word><text> </text><bbox><x1>172</x1><y1>269</y1><x2>178</x2><y2>294</y2></bbox></word><word><text>កម្ពុជា</text><bbox><x1>178</x1><y1>269</y1><x2>228</x2><y2>306</y2></bbox></word><word><text>ដែល</text><bbox><x1>228</x1><y1>269</y1><x2>270</x2><y2>294</y2></bbox></word><word><text>នៅ</text><bbox><x1>270</x1><y1>269</y1><x2>298</x2><y2>294</y2></bbox></word><word><text>ដាច់</text><bbox><x1>298</x1><y1>269</y1><x2>333</x2><y2>294</y2></bbox></word><word><text>យ៉ាង</text><bbox><x1>333</x1><y1>269</y1><x2>375</x2><y2>294</y2></bbox></word><word><text>ឆ្ងាយ</text><bbox><x1>375</x1><y1>269</y1><x2>417</x2><y2>301</y2></bbox></word><word><text>ពី</text><bbox><x1>417</x1><y1>269</y1><x2>431</x2><y2>294</y2></bbox></word><word><text>គេ</text><bbox><x1>431</x1><y1>269</y1><x2>452</x2><y2>294</y2></bbox></word><word><text>ឯង</text><bbox><x1>452</x1><y1>269</y1><x2>480</x2><y2>294</y2></bbox></word></metadata>