<?xml version='1.0' encoding='utf-8'?>
<metadata><image>kh_data_2338.png</image><width>544</width><height>410</height><word><text>ចូលមក</text><bbox><x1>10</x1><y1>10</y1><x2>86</x2><y2>42</y2></bbox></word><word><text>និង</text><bbox><x1>86</x1><y1>10</y1><x2>121</x2><y2>35</y2></bbox></word><word><text>កាប់</text><bbox><x1>121</x1><y1>10</y1><x2>164</x2><y2>35</y2></bbox></word><word><text>បុរស</text><bbox><x1>164</x1><y1>10</y1><x2>213</x2><y2>42</y2></bbox></word><word><text>នោះ</text><bbox><x1>213</x1><y1>10</y1><x2>257</x2><y2>35</y2></bbox></word><word><text> </text><bbox><x1>257</x1><y1>10</y1><x2>263</x2><y2>35</y2></bbox></word><word><text>ឃើញ</text><bbox><x1>263</x1><y1>10</y1><x2>323</x2><y2>42</y2></bbox></word><word><text>ស្ដេច</text><bbox><x1>323</x1><y1>10</y1><x2>372</x2><y2>42</y2></bbox></word><word><text>យាង</text><bbox><x1>372</x1><y1>10</y1><x2>422</x2><y2>35</y2></bbox></word><word><text>ចូលមក</text><bbox><x1>422</x1><y1>10</y1><x2>498</x2><y2>42</y2></bbox></word><word><text>ជិត</text><bbox><x1>498</x1><y1>10</y1><x2>534</x2><y2>35</y2></bbox></word><word><text> </text><bbox><x1>534</x1><y1>10</y1><x2>540</x2><y2>35</y2></bbox></word><word><text>ក៏</text><bbox><x1>10</x1><y1>49</y1><x2>28</x2><y2>74</y2></bbox></word><word><text>ស្ទុះ</text><bbox><x1>28</x1><y1>49</y1><x2>60</x2><y2>88</y2></bbox></word><word><text>ចូលទៅ</text><bbox><x1>60</x1><y1>49</y1><x2>135</x2><y2>81</y2></bbox></word><word><text>ចាប់</text><bbox><x1>135</x1><y1>49</y1><x2>178</x2><y2>74</y2></bbox></word><word><text>ស្ដេច</text><bbox><x1>178</x1><y1>49</y1><x2>227</x2><y2>81</y2></bbox></word><word><text>នោះ</text><bbox><x1>227</x1><y1>49</y1><x2>271</x2><y2>74</y2></bbox></word><word><text>ជាប់</text><bbox><x1>271</x1><y1>49</y1><x2>314</x2><y2>74</y2></bbox></word><word><text> </text><bbox><x1>314</x1><y1>49</y1><x2>320</x2><y2>74</y2></bbox></word><word><text>ហើយក៏</text><bbox><x1>320</x1><y1>49</y1><x2>397</x2><y2>74</y2></bbox></word><word><text>ចាក់</text><bbox><x1>397</x1><y1>49</y1><x2>441</x2><y2>74</y2></bbox></word><word><text>នឹង</text><bbox><x1>441</x1><y1>49</y1><x2>476</x2><y2>74</y2></bbox></word><word><text>កាំបិត</text><bbox><x1>476</x1><y1>49</y1><x2>537</x2><y2>74</y2></bbox></word><word><text>ប</text><bbox><x1>10</x1><y1>88</y1><x2>28</x2><y2>113</y2></bbox></word><word><text>ន្ទោះប</text><bbox><x1>28</x1><y1>88</y1><x2>90</x2><y2>120</y2></bbox></word><word><text>ង្ខុស</text><bbox><x1>90</x1><y1>88</y1><x2>130</x2><y2>127</y2></bbox></word><word><text>ពីរ</text><bbox><x1>130</x1><y1>88</y1><x2>156</x2><y2>113</y2></bbox></word><word><text>បី</text><bbox><x1>156</x1><y1>88</y1><x2>174</x2><y2>113</y2></bbox></word><word><text>ដង</text><bbox><x1>174</x1><y1>88</y1><x2>209</x2><y2>113</y2></bbox></word><word><text> </text><bbox><x1>209</x1><y1>88</y1><x2>215</x2><y2>113</y2></bbox></word><word><text>។</text><bbox><x1>215</x1><y1>88</y1><x2>230</x2><y2>113</y2></bbox></word><word><text> </text><bbox><x1>230</x1><y1>88</y1><x2>236</x2><y2>113</y2></bbox></word><word><text>ហើយ</text><bbox><x1>236</x1><y1>88</y1><x2>295</x2><y2>113</y2></bbox></word><word><text>សួរ</text><bbox><x1>295</x1><y1>88</y1><x2>327</x2><y2>120</y2></bbox></word><word><text>ថា</text><bbox><x1>327</x1><y1>88</y1><x2>353</x2><y2>113</y2></bbox></word><word><text> </text><bbox><x1>353</x1><y1>88</y1><x2>359</x2><y2>113</y2></bbox></word><word><text>នរណា</text><bbox><x1>359</x1><y1>88</y1><x2>425</x2><y2>113</y2></bbox></word><word><text>ចូលមក</text><bbox><x1>425</x1><y1>88</y1><x2>501</x2><y2>120</y2></bbox></word><word><text>ទាំង</text><bbox><x1>501</x1><y1>88</y1><x2>544</x2><y2>113</y2></bbox></word><word><text>យប់</text><bbox><x1>10</x1><y1>127</y1><x2>53</x2><y2>152</y2></bbox></word><word><text>នោះ</text><bbox><x1>53</x1><y1>127</y1><x2>97</x2><y2>152</y2></bbox></word><word><text> </text><bbox><x1>97</x1><y1>127</y1><x2>103</x2><y2>152</y2></bbox></word><word><text>?</text><bbox><x1>103</x1><y1>127</y1><x2>118</x2><y2>152</y2></bbox></word><word><text> </text><bbox><x1>118</x1><y1>127</y1><x2>124</x2><y2>152</y2></bbox></word><word><text>ស្ដេច</text><bbox><x1>124</x1><y1>127</y1><x2>173</x2><y2>159</y2></bbox></word><word><text>ទ្រង់</text><bbox><x1>173</x1><y1>127</y1><x2>216</x2><y2>159</y2></bbox></word><word><text>ឲ្យ</text><bbox><x1>216</x1><y1>127</y1><x2>242</x2><y2>159</y2></bbox></word><word><text>អញ</text><bbox><x1>242</x1><y1>127</y1><x2>285</x2><y2>159</y2></bbox></word><word><text>ចាំ</text><bbox><x1>285</x1><y1>127</y1><x2>311</x2><y2>152</y2></bbox></word><word><text>យាម</text><bbox><x1>311</x1><y1>127</y1><x2>361</x2><y2>152</y2></bbox></word><word><text>ក្នុង</text><bbox><x1>361</x1><y1>127</y1><x2>396</x2><y2>166</y2></bbox></word><word><text>យប់</text><bbox><x1>396</x1><y1>127</y1><x2>439</x2><y2>152</y2></bbox></word><word><text>នេះ</text><bbox><x1>439</x1><y1>127</y1><x2>475</x2><y2>152</y2></bbox></word><word><text> </text><bbox><x1>475</x1><y1>127</y1><x2>481</x2><y2>152</y2></bbox></word><word><text>?</text><bbox><x1>481</x1><y1>127</y1><x2>496</x2><y2>152</y2></bbox></word><word><text> </text><bbox><x1>496</x1><y1>127</y1><x2>502</x2><y2>152</y2></bbox></word><word><text>ស្ដេច</text><bbox><x1>10</x1><y1>166</y1><x2>59</x2><y2>198</y2></bbox></word><word><text>ទ្រង់</text><bbox><x1>59</x1><y1>166</y1><x2>102</x2><y2>198</y2></bbox></word><word><text>ឲ្យ</text><bbox><x1>102</x1><y1>166</y1><x2>128</x2><y2>198</y2></bbox></word><word><text>អញ</text><bbox><x1>128</x1><y1>166</y1><x2>171</x2><y2>198</y2></bbox></word><word><text>ចាំ</text><bbox><x1>171</x1><y1>166</y1><x2>197</x2><y2>191</y2></bbox></word><word><text>យាម</text><bbox><x1>197</x1><y1>166</y1><x2>247</x2><y2>191</y2></bbox></word><word><text>ក្នុង</text><bbox><x1>247</x1><y1>166</y1><x2>282</x2><y2>205</y2></bbox></word><word><text>យប់</text><bbox><x1>282</x1><y1>166</y1><x2>325</x2><y2>191</y2></bbox></word><word><text>នេថា</text><bbox><x1>325</x1><y1>166</y1><x2>377</x2><y2>191</y2></bbox></word><word><text>ហើយ</text><bbox><x1>377</x1><y1>166</y1><x2>436</x2><y2>191</y2></bbox></word><word><text> </text><bbox><x1>436</x1><y1>166</y1><x2>442</x2><y2>191</y2></bbox></word><word><text>ក៏</text><bbox><x1>442</x1><y1>166</y1><x2>460</x2><y2>191</y2></bbox></word><word><text>ចាក់</text><bbox><x1>460</x1><y1>166</y1><x2>504</x2><y2>191</y2></bbox></word><word><text>បង្ខុស</text><bbox><x1>10</x1><y1>205</y1><x2>68</x2><y2>244</y2></bbox></word><word><text>ទៀត</text><bbox><x1>68</x1><y1>205</y1><x2>117</x2><y2>237</y2></bbox></word><word><text> </text><bbox><x1>117</x1><y1>205</y1><x2>123</x2><y2>230</y2></bbox></word><word><text>។</text><bbox><x1>123</x1><y1>205</y1><x2>138</x2><y2>230</y2></bbox></word><word><text> </text><bbox><x1>138</x1><y1>205</y1><x2>144</x2><y2>230</y2></bbox></word><word><text>ស្ដេច</text><bbox><x1>144</x1><y1>205</y1><x2>193</x2><y2>237</y2></bbox></word><word><text>ទ្រង់</text><bbox><x1>193</x1><y1>205</y1><x2>236</x2><y2>237</y2></bbox></word><word><text>មាន</text><bbox><x1>236</x1><y1>205</y1><x2>278</x2><y2>230</y2></bbox></word><word><text>ព្រះបន្ទូល</text><bbox><x1>278</x1><y1>205</y1><x2>371</x2><y2>244</y2></bbox></word><word><text>ថា</text><bbox><x1>371</x1><y1>205</y1><x2>397</x2><y2>230</y2></bbox></word><word><text> </text><bbox><x1>397</x1><y1>205</y1><x2>403</x2><y2>230</y2></bbox></word><word><text>ទេ</text><bbox><x1>403</x1><y1>205</y1><x2>429</x2><y2>230</y2></bbox></word><word><text>អញ</text><bbox><x1>429</x1><y1>205</y1><x2>472</x2><y2>237</y2></bbox></word><word><text>ទ</text><bbox><x1>472</x1><y1>205</y1><x2>490</x2><y2>230</y2></bbox></word><word><text>។</text><bbox><x1>490</x1><y1>205</y1><x2>505</x2><y2>230</y2></bbox></word><word><text>នរណា</text><bbox><x1>10</x1><y1>244</y1><x2>76</x2><y2>269</y2></bbox></word><word><text>អញ</text><bbox><x1>76</x1><y1>244</y1><x2>119</x2><y2>276</y2></bbox></word><word><text>ទេ</text><bbox><x1>119</x1><y1>244</y1><x2>145</x2><y2>269</y2></bbox></word><word><text>ៗ</text><bbox><x1>145</x1><y1>244</y1><x2>163</x2><y2>275</y2></bbox></word><word><text>!</text><bbox><x1>163</x1><y1>244</y1><x2>172</x2><y2>269</y2></bbox></word><word><text>អញ</text><bbox><x1>172</x1><y1>244</y1><x2>215</x2><y2>276</y2></bbox></word><word><text>ជាស្ដេ</text><bbox><x1>215</x1><y1>244</y1><x2>272</x2><y2>276</y2></bbox></word><word><text> </text><bbox><x1>272</x1><y1>244</y1><x2>278</x2><y2>269</y2></bbox></word><word><text>។</text><bbox><x1>278</x1><y1>244</y1><x2>293</x2><y2>269</y2></bbox></word><word><text> </text><bbox><x1>293</x1><y1>244</y1><x2>299</x2><y2>269</y2></bbox></word><word><text>ស្ដេច</text><bbox><x1>299</x1><y1>244</y1><x2>348</x2><y2>276</y2></bbox></word><word><text>អី</text><bbox><x1>348</x1><y1>244</y1><x2>366</x2><y2>269</y2></bbox></word><word><text>មក</text><bbox><x1>366</x1><y1>244</y1><x2>402</x2><y2>269</y2></bbox></word><word><text>ពេលនេះ</text><bbox><x1>402</x1><y1>244</y1><x2>487</x2><y2>269</y2></bbox></word><word><text>,</text><bbox><x1>487</x1><y1>244</y1><x2>493</x2><y2>272</y2></bbox></word></metadata>