<?xml version='1.0' encoding='utf-8'?>
<metadata><image>kh_data_1910.png</image><width>475</width><height>390</height><word><text>អាជ័យ</text><bbox><x1>10</x1><y1>10</y1><x2>67</x2><y2>35</y2></bbox></word><word><text>នេះ</text><bbox><x1>67</x1><y1>10</y1><x2>97</x2><y2>35</y2></bbox></word><word><text>ហៅ</text><bbox><x1>97</x1><y1>10</y1><x2>132</x2><y2>35</y2></bbox></word><word><text>ពេញ</text><bbox><x1>132</x1><y1>10</y1><x2>174</x2><y2>41</y2></bbox></word><word><text>ជា</text><bbox><x1>174</x1><y1>10</y1><x2>195</x2><y2>35</y2></bbox></word><word><text>កាច</text><bbox><x1>195</x1><y1>10</y1><x2>230</x2><y2>35</y2></bbox></word><word><text>ណាស់</text><bbox><x1>230</x1><y1>10</y1><x2>286</x2><y2>35</y2></bbox></word><word><text> </text><bbox><x1>286</x1><y1>10</y1><x2>292</x2><y2>35</y2></bbox></word><word><text>បើ</text><bbox><x1>292</x1><y1>10</y1><x2>313</x2><y2>35</y2></bbox></word><word><text>ដូច្នោះ</text><bbox><x1>313</x1><y1>10</y1><x2>365</x2><y2>42</y2></bbox></word><word><text> </text><bbox><x1>365</x1><y1>10</y1><x2>371</x2><y2>35</y2></bbox></word><word><text>តើ</text><bbox><x1>371</x1><y1>10</y1><x2>392</x2><y2>35</y2></bbox></word><word><text>នឹង</text><bbox><x1>392</x1><y1>10</y1><x2>420</x2><y2>35</y2></bbox></word><word><text>ប្រើ</text><bbox><x1>420</x1><y1>10</y1><x2>448</x2><y2>41</y2></bbox></word><word><text>ការ</text><bbox><x1>10</x1><y1>47</y1><x2>38</x2><y2>72</y2></bbox></word><word><text>អ្វី</text><bbox><x1>38</x1><y1>47</y1><x2>52</x2><y2>79</y2></bbox></word><word><text>បាន</text><bbox><x1>52</x1><y1>47</y1><x2>87</x2><y2>74</y2></bbox></word><word><text> </text><bbox><x1>87</x1><y1>47</y1><x2>93</x2><y2>72</y2></bbox></word><word><text>ទើប</text><bbox><x1>93</x1><y1>47</y1><x2>129</x2><y2>72</y2></bbox></word><word><text>មហាសេដ្ឋី</text><bbox><x1>129</x1><y1>47</y1><x2>213</x2><y2>79</y2></bbox></word><word><text>គិត</text><bbox><x1>213</x1><y1>47</y1><x2>241</x2><y2>72</y2></bbox></word><word><text>ថា</text><bbox><x1>241</x1><y1>47</y1><x2>262</x2><y2>72</y2></bbox></word><word><text> </text><bbox><x1>262</x1><y1>47</y1><x2>268</x2><y2>72</y2></bbox></word><word><text>មាន</text><bbox><x1>268</x1><y1>47</y1><x2>304</x2><y2>72</y2></bbox></word><word><text>តែ</text><bbox><x1>304</x1><y1>47</y1><x2>325</x2><y2>72</y2></bbox></word><word><text>ប្រើ</text><bbox><x1>325</x1><y1>47</y1><x2>353</x2><y2>78</y2></bbox></word><word><text>វា</text><bbox><x1>353</x1><y1>47</y1><x2>367</x2><y2>72</y2></bbox></word><word><text>ឱ្យ</text><bbox><x1>367</x1><y1>47</y1><x2>388</x2><y2>79</y2></bbox></word><word><text>ឃ្វាល</text><bbox><x1>388</x1><y1>47</y1><x2>437</x2><y2>79</y2></bbox></word><word><text>គោ</text><bbox><x1>437</x1><y1>47</y1><x2>465</x2><y2>72</y2></bbox></word><word><text>វិញ</text><bbox><x1>10</x1><y1>84</y1><x2>40</x2><y2>115</y2></bbox></word><word><text> </text><bbox><x1>40</x1><y1>84</y1><x2>46</x2><y2>109</y2></bbox></word><word><text>ទើប</text><bbox><x1>46</x1><y1>84</y1><x2>82</x2><y2>109</y2></bbox></word><word><text>មហាសេដ្ឋី</text><bbox><x1>82</x1><y1>84</y1><x2>166</x2><y2>116</y2></bbox></word><word><text>ហៅ</text><bbox><x1>166</x1><y1>84</y1><x2>201</x2><y2>109</y2></bbox></word><word><text>ថា</text><bbox><x1>201</x1><y1>84</y1><x2>222</x2><y2>109</y2></bbox></word><word><text> </text><bbox><x1>222</x1><y1>84</y1><x2>228</x2><y2>109</y2></bbox></word><word><text>អាជ័យ</text><bbox><x1>228</x1><y1>84</y1><x2>285</x2><y2>109</y2></bbox></word><word><text>អាឯង</text><bbox><x1>285</x1><y1>84</y1><x2>335</x2><y2>109</y2></bbox></word><word><text>មក</text><bbox><x1>335</x1><y1>84</y1><x2>364</x2><y2>109</y2></bbox></word><word><text>ឯណេះ</text><bbox><x1>364</x1><y1>84</y1><x2>422</x2><y2>109</y2></bbox></word><word><text> </text><bbox><x1>422</x1><y1>84</y1><x2>428</x2><y2>109</y2></bbox></word><word><text>ធន</text><bbox><x1>428</x1><y1>84</y1><x2>456</x2><y2>109</y2></bbox></word><word><text>ញ្ជ័យ</text><bbox><x1>10</x1><y1>121</y1><x2>52</x2><y2>153</y2></bbox></word><word><text>ឭ</text><bbox><x1>52</x1><y1>121</y1><x2>66</x2><y2>152</y2></bbox></word><word><text>ហើយ</text><bbox><x1>66</x1><y1>121</y1><x2>115</x2><y2>146</y2></bbox></word><word><text>ឆ្លើយ</text><bbox><x1>115</x1><y1>121</y1><x2>157</x2><y2>153</y2></bbox></word><word><text>ថា</text><bbox><x1>157</x1><y1>121</y1><x2>178</x2><y2>146</y2></bbox></word><word><text> </text><bbox><x1>178</x1><y1>121</y1><x2>184</x2><y2>146</y2></bbox></word><word><text>បាទ</text><bbox><x1>184</x1><y1>121</y1><x2>219</x2><y2>148</y2></bbox></word><word><text> </text><bbox><x1>219</x1><y1>121</y1><x2>225</x2><y2>146</y2></bbox></word><word><text>ហើយ</text><bbox><x1>225</x1><y1>121</y1><x2>274</x2><y2>146</y2></bbox></word><word><text>ដើរ</text><bbox><x1>274</x1><y1>121</y1><x2>302</x2><y2>146</y2></bbox></word><word><text>ចូល</text><bbox><x1>302</x1><y1>121</y1><x2>337</x2><y2>153</y2></bbox></word><word><text>ទៅដល់</text><bbox><x1>337</x1><y1>121</y1><x2>400</x2><y2>146</y2></bbox></word><word><text>ហើយ</text><bbox><x1>400</x1><y1>121</y1><x2>449</x2><y2>146</y2></bbox></word><word><text>អង្គុយ</text><bbox><x1>10</x1><y1>158</y1><x2>60</x2><y2>195</y2></bbox></word><word><text>នៅ</text><bbox><x1>60</x1><y1>158</y1><x2>88</x2><y2>183</y2></bbox></word><word><text>ស្ងៀម</text><bbox><x1>88</x1><y1>158</y1><x2>137</x2><y2>195</y2></bbox></word><word><text> </text><bbox><x1>137</x1><y1>158</y1><x2>143</x2><y2>183</y2></bbox></word><word><text>ឯ</text><bbox><x1>143</x1><y1>158</y1><x2>157</x2><y2>183</y2></bbox></word><word><text>មហាសេដ្ឋី</text><bbox><x1>157</x1><y1>158</y1><x2>241</x2><y2>190</y2></bbox></word><word><text>ប្រាប់</text><bbox><x1>241</x1><y1>158</y1><x2>283</x2><y2>189</y2></bbox></word><word><text>ថា</text><bbox><x1>283</x1><y1>158</y1><x2>304</x2><y2>183</y2></bbox></word><word><text> </text><bbox><x1>304</x1><y1>158</y1><x2>310</x2><y2>183</y2></bbox></word><word><text>អាជ័យ</text><bbox><x1>310</x1><y1>158</y1><x2>367</x2><y2>183</y2></bbox></word><word><text>ទៅ</text><bbox><x1>367</x1><y1>158</y1><x2>395</x2><y2>183</y2></bbox></word><word><text>ឃ្វាល</text><bbox><x1>395</x1><y1>158</y1><x2>444</x2><y2>190</y2></bbox></word><word><text>គោ</text><bbox><x1>444</x1><y1>158</y1><x2>472</x2><y2>183</y2></bbox></word><word><text>សព្វ</text><bbox><x1>10</x1><y1>195</y1><x2>45</x2><y2>227</y2></bbox></word><word><text>ៗ</text><bbox><x1>45</x1><y1>195</y1><x2>60</x2><y2>220</y2></bbox></word><word><text>ថ្ងៃ</text><bbox><x1>60</x1><y1>195</y1><x2>81</x2><y2>227</y2></bbox></word><word><text>កុំ</text><bbox><x1>81</x1><y1>195</y1><x2>95</x2><y2>227</y2></bbox></word><word><text>ឱ្យ</text><bbox><x1>95</x1><y1>195</y1><x2>116</x2><y2>227</y2></bbox></word><word><text>ខាន</text><bbox><x1>116</x1><y1>195</y1><x2>151</x2><y2>220</y2></bbox></word><word><text>ឡើយ</text><bbox><x1>151</x1><y1>195</y1><x2>200</x2><y2>227</y2></bbox></word><word><text> </text><bbox><x1>200</x1><y1>195</y1><x2>206</x2><y2>220</y2></bbox></word><word><text>ធន</text><bbox><x1>206</x1><y1>195</y1><x2>234</x2><y2>220</y2></bbox></word><word><text>ញ្ជ័យ</text><bbox><x1>234</x1><y1>195</y1><x2>276</x2><y2>227</y2></bbox></word><word><text>ស្ដាប់</text><bbox><x1>276</x1><y1>195</y1><x2>318</x2><y2>227</y2></bbox></word><word><text>ហើយក៏</text><bbox><x1>318</x1><y1>195</y1><x2>381</x2><y2>220</y2></bbox></word><word><text>ជម្រាប</text><bbox><x1>381</x1><y1>195</y1><x2>438</x2><y2>226</y2></bbox></word><word><text>មហាសេដ្ឋី</text><bbox><x1>10</x1><y1>232</y1><x2>94</x2><y2>264</y2></bbox></word><word><text>ថា</text><bbox><x1>94</x1><y1>232</y1><x2>115</x2><y2>257</y2></bbox></word><word><text> </text><bbox><x1>115</x1><y1>232</y1><x2>121</x2><y2>257</y2></bbox></word><word><text>ត្បិត</text><bbox><x1>121</x1><y1>232</y1><x2>156</x2><y2>264</y2></bbox></word><word><text>ខ្លួន</text><bbox><x1>156</x1><y1>232</y1><x2>184</x2><y2>269</y2></bbox></word><word><text>ខ្ញុំបាទ</text><bbox><x1>184</x1><y1>232</y1><x2>233</x2><y2>269</y2></bbox></word><word><text>ឥត</text><bbox><x1>233</x1><y1>232</y1><x2>261</x2><y2>257</y2></bbox></word><word><text>មាន</text><bbox><x1>261</x1><y1>232</y1><x2>297</x2><y2>257</y2></bbox></word><word><text>ប្រពន្ធ</text><bbox><x1>297</x1><y1>232</y1><x2>347</x2><y2>264</y2></bbox></word><word><text> </text><bbox><x1>347</x1><y1>232</y1><x2>353</x2><y2>257</y2></bbox></word><word><text>ឥឡូវនេះ</text><bbox><x1>353</x1><y1>232</y1><x2>426</x2><y2>269</y2></bbox></word><word><text>លោក</text><bbox><x1>426</x1><y1>232</y1><x2>475</x2><y2>257</y2></bbox></word><word><text>តា</text><bbox><x1>10</x1><y1>269</y1><x2>31</x2><y2>294</y2></bbox></word><word><text>ឱ្យ</text><bbox><x1>31</x1><y1>269</y1><x2>52</x2><y2>301</y2></bbox></word><word><text>ទៅ</text><bbox><x1>52</x1><y1>269</y1><x2>80</x2><y2>294</y2></bbox></word><word><text>ឃ្វាល</text><bbox><x1>80</x1><y1>269</y1><x2>129</x2><y2>301</y2></bbox></word><word><text>គោ</text><bbox><x1>129</x1><y1>269</y1><x2>157</x2><y2>294</y2></bbox></word><word><text>នោះ</text><bbox><x1>157</x1><y1>269</y1><x2>194</x2><y2>294</y2></bbox></word></metadata>