<?xml version='1.0' encoding='utf-8'?>
<metadata><image>kh_data_1009.png</image><width>520</width><height>390</height><word><text>មួយចំនួន</text><bbox><x1>10</x1><y1>10</y1><x2>85</x2><y2>42</y2></bbox></word><word><text>ផងដែរ</text><bbox><x1>85</x1><y1>10</y1><x2>139</x2><y2>35</y2></bbox></word><word><text>។</text><bbox><x1>139</x1><y1>10</y1><x2>152</x2><y2>35</y2></bbox></word><word><text> </text><bbox><x1>152</x1><y1>10</y1><x2>158</x2><y2>35</y2></bbox></word><word><text>នាយ</text><bbox><x1>158</x1><y1>10</y1><x2>198</x2><y2>35</y2></bbox></word><word><text>ឧត្តមសេនីយ៍</text><bbox><x1>198</x1><y1>10</y1><x2>299</x2><y2>42</y2></bbox></word><word><text> </text><bbox><x1>299</x1><y1>10</y1><x2>305</x2><y2>35</y2></bbox></word><word><text>សែម</text><bbox><x1>305</x1><y1>10</y1><x2>345</x2><y2>35</y2></bbox></word><word><text> </text><bbox><x1>345</x1><y1>10</y1><x2>351</x2><y2>35</y2></bbox></word><word><text>សុវណ្ណ</text><bbox><x1>351</x1><y1>10</y1><x2>404</x2><y2>42</y2></bbox></word><word><text>នី</text><bbox><x1>404</x1><y1>10</y1><x2>418</x2><y2>35</y2></bbox></word><word><text> </text><bbox><x1>418</x1><y1>10</y1><x2>424</x2><y2>35</y2></bbox></word><word><text>បាន</text><bbox><x1>424</x1><y1>10</y1><x2>458</x2><y2>37</y2></bbox></word><word><text>ថ្លែង</text><bbox><x1>458</x1><y1>10</y1><x2>492</x2><y2>42</y2></bbox></word><word><text>ថា</text><bbox><x1>492</x1><y1>10</y1><x2>512</x2><y2>35</y2></bbox></word><word><text> </text><bbox><x1>512</x1><y1>10</y1><x2>518</x2><y2>35</y2></bbox></word><word><text>កង</text><bbox><x1>10</x1><y1>48</y1><x2>37</x2><y2>73</y2></bbox></word><word><text>វិស្វកម្ម</text><bbox><x1>37</x1><y1>48</y1><x2>91</x2><y2>80</y2></bbox></word><word><text>លេខ</text><bbox><x1>91</x1><y1>48</y1><x2>131</x2><y2>73</y2></bbox></word><word><text>៤២៣</text><bbox><x1>131</x1><y1>48</y1><x2>181</x2><y2>73</y2></bbox></word><word><text> </text><bbox><x1>181</x1><y1>48</y1><x2>187</x2><y2>73</y2></bbox></word><word><text>ជា</text><bbox><x1>187</x1><y1>48</y1><x2>207</x2><y2>73</y2></bbox></word><word><text>កង</text><bbox><x1>207</x1><y1>48</y1><x2>234</x2><y2>73</y2></bbox></word><word><text>ទី៩</text><bbox><x1>234</x1><y1>48</y1><x2>263</x2><y2>73</y2></bbox></word><word><text> </text><bbox><x1>263</x1><y1>48</y1><x2>269</x2><y2>73</y2></bbox></word><word><text>ដែល</text><bbox><x1>269</x1><y1>48</y1><x2>309</x2><y2>73</y2></bbox></word><word><text>ត្រៀម</text><bbox><x1>309</x1><y1>48</y1><x2>355</x2><y2>80</y2></bbox></word><word><text>ហោះហើរ</text><bbox><x1>355</x1><y1>48</y1><x2>430</x2><y2>73</y2></bbox></word><word><text>ទៅ</text><bbox><x1>430</x1><y1>48</y1><x2>456</x2><y2>73</y2></bbox></word><word><text>បំពេញ</text><bbox><x1>456</x1><y1>48</y1><x2>510</x2><y2>79</y2></bbox></word><word><text>បេសកកម្ម</text><bbox><x1>10</x1><y1>86</y1><x2>91</x2><y2>118</y2></bbox></word><word><text>នៅ</text><bbox><x1>91</x1><y1>86</y1><x2>117</x2><y2>111</y2></bbox></word><word><text>សាធារណរដ្ឋ</text><bbox><x1>117</x1><y1>86</y1><x2>216</x2><y2>118</y2></bbox></word><word><text>អាហ្រ្វិក</text><bbox><x1>216</x1><y1>86</y1><x2>276</x2><y2>123</y2></bbox></word><word><text>កណ្តាល</text><bbox><x1>276</x1><y1>86</y1><x2>343</x2><y2>118</y2></bbox></word><word><text>នេះ</text><bbox><x1>343</x1><y1>86</y1><x2>372</x2><y2>111</y2></bbox></word><word><text> </text><bbox><x1>372</x1><y1>86</y1><x2>378</x2><y2>111</y2></bbox></word><word><text>មាន</text><bbox><x1>378</x1><y1>86</y1><x2>412</x2><y2>111</y2></bbox></word><word><text>ចំនួន</text><bbox><x1>412</x1><y1>86</y1><x2>453</x2><y2>118</y2></bbox></word><word><text>សរុប</text><bbox><x1>453</x1><y1>86</y1><x2>493</x2><y2>118</y2></bbox></word><word><text> </text><bbox><x1>493</x1><y1>86</y1><x2>499</x2><y2>111</y2></bbox></word><word><text>២៤៤</text><bbox><x1>10</x1><y1>124</y1><x2>57</x2><y2>149</y2></bbox></word><word><text>នាក់</text><bbox><x1>57</x1><y1>124</y1><x2>91</x2><y2>149</y2></bbox></word><word><text> </text><bbox><x1>91</x1><y1>124</y1><x2>97</x2><y2>149</y2></bbox></word><word><text>ដោយ</text><bbox><x1>97</x1><y1>124</y1><x2>143</x2><y2>149</y2></bbox></word><word><text>មាន</text><bbox><x1>143</x1><y1>124</y1><x2>177</x2><y2>149</y2></bbox></word><word><text>នារី</text><bbox><x1>177</x1><y1>124</y1><x2>205</x2><y2>149</y2></bbox></word><word><text> </text><bbox><x1>205</x1><y1>124</y1><x2>211</x2><y2>149</y2></bbox></word><word><text>៣០</text><bbox><x1>211</x1><y1>124</y1><x2>244</x2><y2>149</y2></bbox></word><word><text>នាក់</text><bbox><x1>244</x1><y1>124</y1><x2>278</x2><y2>149</y2></bbox></word><word><text> </text><bbox><x1>278</x1><y1>124</y1><x2>284</x2><y2>149</y2></bbox></word><word><text>ដែល</text><bbox><x1>284</x1><y1>124</y1><x2>324</x2><y2>149</y2></bbox></word><word><text>មកពី</text><bbox><x1>324</x1><y1>124</y1><x2>365</x2><y2>149</y2></bbox></word><word><text>បណ្តា</text><bbox><x1>365</x1><y1>124</y1><x2>412</x2><y2>156</y2></bbox></word><word><text>៤០</text><bbox><x1>412</x1><y1>124</y1><x2>442</x2><y2>149</y2></bbox></word><word><text>កង</text><bbox><x1>442</x1><y1>124</y1><x2>469</x2><y2>149</y2></bbox></word><word><text>ឯកភាព</text><bbox><x1>10</x1><y1>162</y1><x2>71</x2><y2>187</y2></bbox></word><word><text> </text><bbox><x1>71</x1><y1>162</y1><x2>77</x2><y2>187</y2></bbox></word><word><text>នៃ</text><bbox><x1>77</x1><y1>162</y1><x2>97</x2><y2>187</y2></bbox></word><word><text>កងយោធពល</text><bbox><x1>97</x1><y1>162</y1><x2>204</x2><y2>187</y2></bbox></word><word><text>ខេមរភូមិន្ទ</text><bbox><x1>204</x1><y1>162</y1><x2>285</x2><y2>194</y2></bbox></word><word><text>។</text><bbox><x1>285</x1><y1>162</y1><x2>298</x2><y2>187</y2></bbox></word><word><text> </text><bbox><x1>298</x1><y1>162</y1><x2>304</x2><y2>187</y2></bbox></word><word><text>កងកម្លាំង</text><bbox><x1>304</x1><y1>162</y1><x2>379</x2><y2>194</y2></bbox></word><word><text> </text><bbox><x1>379</x1><y1>162</y1><x2>385</x2><y2>187</y2></bbox></word><word><text>ដែល</text><bbox><x1>385</x1><y1>162</y1><x2>425</x2><y2>187</y2></bbox></word><word><text>នឹង</text><bbox><x1>425</x1><y1>162</y1><x2>452</x2><y2>187</y2></bbox></word><word><text>ចេញ</text><bbox><x1>452</x1><y1>162</y1><x2>492</x2><y2>193</y2></bbox></word><word><text>បំពេញ</text><bbox><x1>10</x1><y1>200</y1><x2>64</x2><y2>231</y2></bbox></word><word><text>បេសកកម្ម</text><bbox><x1>64</x1><y1>200</y1><x2>145</x2><y2>232</y2></bbox></word><word><text>ក្នុង</text><bbox><x1>145</x1><y1>200</y1><x2>172</x2><y2>238</y2></bbox></word><word><text>ឆ្នាំ</text><bbox><x1>172</x1><y1>200</y1><x2>192</x2><y2>232</y2></bbox></word><word><text>៩នេះ</text><bbox><x1>192</x1><y1>200</y1><x2>236</x2><y2>225</y2></bbox></word><word><text> </text><bbox><x1>236</x1><y1>200</y1><x2>242</x2><y2>225</y2></bbox></word><word><text>សុទ្ធតែ</text><bbox><x1>242</x1><y1>200</y1><x2>295</x2><y2>232</y2></bbox></word><word><text>បាន</text><bbox><x1>295</x1><y1>200</y1><x2>329</x2><y2>227</y2></bbox></word><word><text>ទទួល</text><bbox><x1>329</x1><y1>200</y1><x2>376</x2><y2>232</y2></bbox></word><word><text>ការហ្វឹកហ្វឺន</text><bbox><x1>376</x1><y1>200</y1><x2>470</x2><y2>232</y2></bbox></word><word><text>មុន</text><bbox><x1>470</x1><y1>200</y1><x2>497</x2><y2>232</y2></bbox></word><word><text>ចល័ត</text><bbox><x1>10</x1><y1>238</y1><x2>57</x2><y2>263</y2></bbox></word><word><text> </text><bbox><x1>57</x1><y1>238</y1><x2>63</x2><y2>263</y2></bbox></word><word><text>និង</text><bbox><x1>63</x1><y1>238</y1><x2>90</x2><y2>263</y2></bbox></word><word><text>លើ</text><bbox><x1>90</x1><y1>238</y1><x2>116</x2><y2>263</y2></bbox></word><word><text>ជំនាញ</text><bbox><x1>116</x1><y1>238</y1><x2>170</x2><y2>269</y2></bbox></word><word><text>វិជ្ជាជីវៈ</text><bbox><x1>170</x1><y1>238</y1><x2>225</x2><y2>270</y2></bbox></word><word><text>ប្រកបដោយ</text><bbox><x1>225</x1><y1>238</y1><x2>319</x2><y2>270</y2></bbox></word><word><text>គុណភាព</text><bbox><x1>319</x1><y1>238</y1><x2>393</x2><y2>270</y2></bbox></word><word><text> </text><bbox><x1>393</x1><y1>238</y1><x2>399</x2><y2>263</y2></bbox></word><word><text>ពី</text><bbox><x1>399</x1><y1>238</y1><x2>413</x2><y2>263</y2></bbox></word><word><text>គ្រូបង្គោល</text><bbox><x1>413</x1><y1>238</y1><x2>493</x2><y2>270</y2></bbox></word><word><text>កម្ពុជា</text><bbox><x1>10</x1><y1>276</y1><x2>57</x2><y2>314</y2></bbox></word><word><text> </text><bbox><x1>57</x1><y1>276</y1><x2>63</x2><y2>301</y2></bbox></word><word><text>និង</text><bbox><x1>63</x1><y1>276</y1><x2>90</x2><y2>301</y2></bbox></word><word><text>ពី</text><bbox><x1>90</x1><y1>276</y1><x2>104</x2><y2>301</y2></bbox></word><word><text>បណ្តា</text><bbox><x1>104</x1><y1>276</y1><x2>151</x2><y2>308</y2></bbox></word><word><text>ប្រទេស</text><bbox><x1>151</x1><y1>276</y1><x2>211</x2><y2>308</y2></bbox></word><word><text>ជា</text><bbox><x1>211</x1><y1>276</y1><x2>231</x2><y2>301</y2></bbox></word><word><text>មិត្ត</text><bbox><x1>231</x1><y1>276</y1><x2>258</x2><y2>308</y2></bbox></word><word><text> </text><bbox><x1>258</x1><y1>276</y1><x2>264</x2><y2>301</y2></bbox></word><word><text>ដើម្បី</text><bbox><x1>264</x1><y1>276</y1><x2>304</x2><y2>308</y2></bbox></word></metadata>