<?xml version='1.0' encoding='utf-8'?>
<metadata><image>kh_data_1790.png</image><width>471</width><height>380</height><word><text>ដែល</text><bbox><x1>10</x1><y1>10</y1><x2>54</x2><y2>34</y2></bbox></word><word><text>នៅ</text><bbox><x1>54</x1><y1>10</y1><x2>84</x2><y2>34</y2></bbox></word><word><text>ជ្រោយ</text><bbox><x1>84</x1><y1>10</y1><x2>144</x2><y2>41</y2></bbox></word><word><text>ចង្វា</text><bbox><x1>144</x1><y1>10</y1><x2>181</x2><y2>40</y2></bbox></word><word><text> </text><bbox><x1>181</x1><y1>10</y1><x2>187</x2><y2>33</y2></bbox></word><word><text>ដើម្បី</text><bbox><x1>187</x1><y1>10</y1><x2>234</x2><y2>40</y2></bbox></word><word><text>ដណេ្ដីម</text><bbox><x1>234</x1><y1>10</y1><x2>311</x2><y2>40</y2></bbox></word><word><text>យក</text><bbox><x1>311</x1><y1>10</y1><x2>351</x2><y2>34</y2></bbox></word><word><text> </text><bbox><x1>351</x1><y1>10</y1><x2>357</x2><y2>33</y2></bbox></word><word><text>ព្រះវរ</text><bbox><x1>357</x1><y1>10</y1><x2>412</x2><y2>41</y2></bbox></word><word><text>រាជ</text><bbox><x1>412</x1><y1>10</y1><x2>441</x2><y2>34</y2></bbox></word><word><text>មាតា</text><bbox><x1>10</x1><y1>47</y1><x2>54</x2><y2>70</y2></bbox></word><word><text>វិញ</text><bbox><x1>54</x1><y1>47</y1><x2>92</x2><y2>77</y2></bbox></word><word><text>។</text><bbox><x1>92</x1><y1>47</y1><x2>106</x2><y2>71</y2></bbox></word><word><text> </text><bbox><x1>106</x1><y1>47</y1><x2>112</x2><y2>70</y2></bbox></word><word><text>មន្រ្ដី</text><bbox><x1>112</x1><y1>47</y1><x2>150</x2><y2>84</y2></bbox></word><word><text>ក៏</text><bbox><x1>150</x1><y1>47</y1><x2>166</x2><y2>71</y2></bbox></word><word><text>ប្រមូល</text><bbox><x1>166</x1><y1>47</y1><x2>227</x2><y2>79</y2></bbox></word><word><text>ទ័ព</text><bbox><x1>227</x1><y1>47</y1><x2>257</x2><y2>71</y2></bbox></word><word><text>បាន</text><bbox><x1>257</x1><y1>47</y1><x2>293</x2><y2>71</y2></bbox></word><word><text>គ្រប់</text><bbox><x1>293</x1><y1>47</y1><x2>332</x2><y2>78</y2></bbox></word><word><text>ចំនួន</text><bbox><x1>332</x1><y1>47</y1><x2>378</x2><y2>79</y2></bbox></word><word><text>ហើយ</text><bbox><x1>378</x1><y1>47</y1><x2>430</x2><y2>71</y2></bbox></word><word><text> </text><bbox><x1>430</x1><y1>47</y1><x2>436</x2><y2>70</y2></bbox></word><word><text>ព្រះអង្គ</text><bbox><x1>10</x1><y1>84</y1><x2>72</x2><y2>115</y2></bbox></word><word><text>ទ្រង់</text><bbox><x1>72</x1><y1>84</y1><x2>110</x2><y2>115</y2></bbox></word><word><text>ព្រះចិន្ដា</text><bbox><x1>110</x1><y1>84</y1><x2>179</x2><y2>115</y2></bbox></word><word><text>ថា</text><bbox><x1>179</x1><y1>84</y1><x2>199</x2><y2>108</y2></bbox></word><word><text> </text><bbox><x1>199</x1><y1>84</y1><x2>205</x2><y2>107</y2></bbox></word><word><text>លើក</text><bbox><x1>205</x1><y1>84</y1><x2>250</x2><y2>108</y2></bbox></word><word><text>ទ័ព</text><bbox><x1>250</x1><y1>84</y1><x2>280</x2><y2>108</y2></bbox></word><word><text>ទៅ</text><bbox><x1>280</x1><y1>84</y1><x2>309</x2><y2>108</y2></bbox></word><word><text>វាយ</text><bbox><x1>309</x1><y1>84</y1><x2>354</x2><y2>107</y2></bbox></word><word><text>ទ័ព</text><bbox><x1>354</x1><y1>84</y1><x2>384</x2><y2>108</y2></bbox></word><word><text>យួន</text><bbox><x1>384</x1><y1>84</y1><x2>423</x2><y2>116</y2></bbox></word><word><text> </text><bbox><x1>423</x1><y1>84</y1><x2>429</x2><y2>107</y2></bbox></word><word><text>ដែល</text><bbox><x1>10</x1><y1>121</y1><x2>54</x2><y2>145</y2></bbox></word><word><text> </text><bbox><x1>54</x1><y1>121</y1><x2>60</x2><y2>144</y2></bbox></word><word><text>មាន</text><bbox><x1>60</x1><y1>121</y1><x2>97</x2><y2>145</y2></bbox></word><word><text>ព្រះរាជ</text><bbox><x1>97</x1><y1>121</y1><x2>157</x2><y2>152</y2></bbox></word><word><text>មាតា</text><bbox><x1>157</x1><y1>121</y1><x2>201</x2><y2>144</y2></bbox></word><word><text>ដែល</text><bbox><x1>201</x1><y1>121</y1><x2>245</x2><y2>145</y2></bbox></word><word><text>នៅ</text><bbox><x1>245</x1><y1>121</y1><x2>275</x2><y2>145</y2></bbox></word><word><text>ជាមួយ</text><bbox><x1>275</x1><y1>121</y1><x2>335</x2><y2>153</y2></bbox></word><word><text>ផង</text><bbox><x1>335</x1><y1>121</y1><x2>364</x2><y2>144</y2></bbox></word><word><text>នោះ</text><bbox><x1>364</x1><y1>121</y1><x2>402</x2><y2>145</y2></bbox></word><word><text>មិន</text><bbox><x1>402</x1><y1>121</y1><x2>433</x2><y2>145</y2></bbox></word><word><text>ស្រួល</text><bbox><x1>10</x1><y1>158</y1><x2>60</x2><y2>190</y2></bbox></word><word><text>ទេ</text><bbox><x1>60</x1><y1>158</y1><x2>82</x2><y2>182</y2></bbox></word><word><text>។</text><bbox><x1>82</x1><y1>158</y1><x2>96</x2><y2>182</y2></bbox></word><word><text> </text><bbox><x1>96</x1><y1>158</y1><x2>102</x2><y2>181</y2></bbox></word><word><text>គិត</text><bbox><x1>102</x1><y1>158</y1><x2>134</x2><y2>182</y2></bbox></word><word><text>ដូច្នោះ</text><bbox><x1>134</x1><y1>158</y1><x2>186</x2><y2>190</y2></bbox></word><word><text> </text><bbox><x1>186</x1><y1>158</y1><x2>192</x2><y2>181</y2></bbox></word><word><text>ព្រះអង្គ</text><bbox><x1>192</x1><y1>158</y1><x2>254</x2><y2>189</y2></bbox></word><word><text>ទ្រង់</text><bbox><x1>254</x1><y1>158</y1><x2>292</x2><y2>189</y2></bbox></word><word><text>កែ</text><bbox><x1>292</x1><y1>158</y1><x2>317</x2><y2>182</y2></bbox></word><word><text>ព្រះរាជ</text><bbox><x1>317</x1><y1>158</y1><x2>377</x2><y2>189</y2></bbox></word><word><text>មធ្យោបាយ</text><bbox><x1>10</x1><y1>195</y1><x2>107</x2><y2>226</y2></bbox></word><word><text>។</text><bbox><x1>107</x1><y1>195</y1><x2>121</x2><y2>219</y2></bbox></word><word><text> </text><bbox><x1>121</x1><y1>195</y1><x2>127</x2><y2>218</y2></bbox></word><word><text>ព្រះអង្គ</text><bbox><x1>127</x1><y1>195</y1><x2>189</x2><y2>226</y2></bbox></word><word><text> </text><bbox><x1>189</x1><y1>195</y1><x2>195</x2><y2>218</y2></bbox></word><word><text>ទ្រង់</text><bbox><x1>195</x1><y1>195</y1><x2>233</x2><y2>226</y2></bbox></word><word><text>ប្រឹក្សា</text><bbox><x1>233</x1><y1>195</y1><x2>288</x2><y2>226</y2></bbox></word><word><text>ជាមួយ</text><bbox><x1>288</x1><y1>195</y1><x2>348</x2><y2>227</y2></bbox></word><word><text>ពញា</text><bbox><x1>348</x1><y1>195</y1><x2>394</x2><y2>225</y2></bbox></word><word><text>មន្រ្ដី</text><bbox><x1>394</x1><y1>195</y1><x2>432</x2><y2>232</y2></bbox></word><word><text>សង្គ្រាម</text><bbox><x1>10</x1><y1>232</y1><x2>75</x2><y2>269</y2></bbox></word><word><text>សួស្ដិ៍</text><bbox><x1>75</x1><y1>232</y1><x2>118</x2><y2>264</y2></bbox></word><word><text> </text><bbox><x1>118</x1><y1>232</y1><x2>124</x2><y2>255</y2></bbox></word><word><text>ដើម្បី</text><bbox><x1>124</x1><y1>232</y1><x2>171</x2><y2>262</y2></bbox></word><word><text>ទៅ</text><bbox><x1>171</x1><y1>232</y1><x2>200</x2><y2>256</y2></bbox></word><word><text>យក</text><bbox><x1>200</x1><y1>232</y1><x2>240</x2><y2>256</y2></bbox></word><word><text>ព្រះវរាជ</text><bbox><x1>240</x1><y1>232</y1><x2>316</x2><y2>263</y2></bbox></word><word><text>មាតា</text><bbox><x1>316</x1><y1>232</y1><x2>360</x2><y2>255</y2></bbox></word><word><text>។</text><bbox><x1>360</x1><y1>232</y1><x2>374</x2><y2>256</y2></bbox></word><word><text> </text><bbox><x1>374</x1><y1>232</y1><x2>380</x2><y2>255</y2></bbox></word><word><text>ចៅ</text><bbox><x1>380</x1><y1>232</y1><x2>410</x2><y2>256</y2></bbox></word><word><text>ពញា</text><bbox><x1>410</x1><y1>232</y1><x2>456</x2><y2>262</y2></bbox></word><word><text>មន្រ្ដី</text><bbox><x1>10</x1><y1>269</y1><x2>48</x2><y2>306</y2></bbox></word><word><text>សង្គ្រាម</text><bbox><x1>48</x1><y1>269</y1><x2>113</x2><y2>306</y2></bbox></word><word><text>សួស្ដិ៍</text><bbox><x1>113</x1><y1>269</y1><x2>156</x2><y2>301</y2></bbox></word><word><text> </text><bbox><x1>156</x1><y1>269</y1><x2>162</x2><y2>292</y2></bbox></word><word><text>ថ្វាយ</text><bbox><x1>162</x1><y1>269</y1><x2>206</x2><y2>299</y2></bbox></word><word><text>ព្រះរាជ</text><bbox><x1>206</x1><y1>269</y1><x2>266</x2><y2>300</y2></bbox></word><word><text> </text><bbox><x1>266</x1><y1>269</y1><x2>272</x2><y2>292</y2></bbox></word><word><text>យោបល់</text><bbox><x1>272</x1><y1>269</y1><x2>346</x2><y2>293</y2></bbox></word><word><text>ថា</text><bbox><x1>346</x1><y1>269</y1><x2>366</x2><y2>293</y2></bbox></word><word><text> </text><bbox><x1>366</x1><y1>269</y1><x2>372</x2><y2>292</y2></bbox></word><word><text>មាន</text><bbox><x1>372</x1><y1>269</y1><x2>409</x2><y2>293</y2></bbox></word><word><text>តែ</text><bbox><x1>409</x1><y1>269</y1><x2>433</x2><y2>293</y2></bbox></word><word><text>ប្អូន</text><bbox><x1>433</x1><y1>269</y1><x2>464</x2><y2>305</y2></bbox></word><word><text>ទូលព្រះបង្គំ</text><bbox><x1>10</x1><y1>306</y1><x2>108</x2><y2>338</y2></bbox></word><word><text>ឈ្មោះ</text><bbox><x1>108</x1><y1>306</y1><x2>159</x2><y2>336</y2></bbox></word><word><text>ពញា</text><bbox><x1>159</x1><y1>306</y1><x2>205</x2><y2>336</y2></bbox></word><word><text>ភក្ដី</text><bbox><x1>205</x1><y1>306</y1><x2>237</x2><y2>336</y2></bbox></word><word><text>សង្គ្រាម</text><bbox><x1>237</x1><y1>306</y1><x2>302</x2><y2>343</y2></bbox></word><word><text>ហុក</text><bbox><x1>302</x1><y1>306</y1><x2>339</x2><y2>339</y2></bbox></word><word><text>ទេ</text><bbox><x1>339</x1><y1>306</y1><x2>361</x2><y2>330</y2></bbox></word></metadata>