<?xml version='1.0' encoding='utf-8'?>
<metadata><image>kh_data_273.png</image><width>614</width><height>310</height><word><text>គណបក្ស</text><bbox><x1>10</x1><y1>10</y1><x2>79</x2><y2>35</y2></bbox></word><word><text>នយោបាយ</text><bbox><x1>79</x1><y1>10</y1><x2>161</x2><y2>31</y2></bbox></word><word><text>ចំនួន</text><bbox><x1>161</x1><y1>10</y1><x2>199</x2><y2>37</y2></bbox></word><word><text>៨</text><bbox><x1>199</x1><y1>10</y1><x2>213</x2><y2>30</y2></bbox></word><word><text> </text><bbox><x1>213</x1><y1>10</y1><x2>220</x2><y2>30</y2></bbox></word><word><text>មាន</text><bbox><x1>220</x1><y1>10</y1><x2>252</x2><y2>30</y2></bbox></word><word><text>ដូច</text><bbox><x1>252</x1><y1>10</y1><x2>277</x2><y2>36</y2></bbox></word><word><text>ខាងក្រោម</text><bbox><x1>277</x1><y1>10</y1><x2>352</x2><y2>35</y2></bbox></word><word><text> </text><bbox><x1>352</x1><y1>10</y1><x2>359</x2><y2>30</y2></bbox></word><word><text>ទី១</text><bbox><x1>359</x1><y1>10</y1><x2>387</x2><y2>30</y2></bbox></word><word><text> </text><bbox><x1>387</x1><y1>10</y1><x2>394</x2><y2>30</y2></bbox></word><word><text>គណបក្ស</text><bbox><x1>394</x1><y1>10</y1><x2>463</x2><y2>35</y2></bbox></word><word><text>ប្រជាជន</text><bbox><x1>463</x1><y1>10</y1><x2>526</x2><y2>35</y2></bbox></word><word><text>កម្ពុជា</text><bbox><x1>526</x1><y1>10</y1><x2>570</x2><y2>39</y2></bbox></word><word><text> </text><bbox><x1>570</x1><y1>10</y1><x2>577</x2><y2>30</y2></bbox></word><word><text>ទី២</text><bbox><x1>577</x1><y1>10</y1><x2>605</x2><y2>30</y2></bbox></word><word><text> </text><bbox><x1>605</x1><y1>10</y1><x2>612</x2><y2>30</y2></bbox></word><word><text>គណបក្ស</text><bbox><x1>10</x1><y1>39</y1><x2>79</x2><y2>64</y2></bbox></word><word><text>យុវជន</text><bbox><x1>79</x1><y1>39</y1><x2>129</x2><y2>66</y2></bbox></word><word><text>កម្ពុជា</text><bbox><x1>129</x1><y1>39</y1><x2>173</x2><y2>68</y2></bbox></word><word><text> </text><bbox><x1>173</x1><y1>39</y1><x2>180</x2><y2>59</y2></bbox></word><word><text>ទី៣</text><bbox><x1>180</x1><y1>39</y1><x2>210</x2><y2>59</y2></bbox></word><word><text> </text><bbox><x1>210</x1><y1>39</y1><x2>217</x2><y2>59</y2></bbox></word><word><text>គណបក្ស</text><bbox><x1>217</x1><y1>39</y1><x2>286</x2><y2>64</y2></bbox></word><word><text>ខ្មែរ</text><bbox><x1>286</x1><y1>39</y1><x2>311</x2><y2>64</y2></bbox></word><word><text>រួបរួម</text><bbox><x1>311</x1><y1>39</y1><x2>350</x2><y2>66</y2></bbox></word><word><text>ជាតិ</text><bbox><x1>350</x1><y1>39</y1><x2>382</x2><y2>59</y2></bbox></word><word><text> </text><bbox><x1>382</x1><y1>39</y1><x2>389</x2><y2>59</y2></bbox></word><word><text>ទី៤</text><bbox><x1>389</x1><y1>39</y1><x2>416</x2><y2>59</y2></bbox></word><word><text> </text><bbox><x1>416</x1><y1>39</y1><x2>423</x2><y2>59</y2></bbox></word><word><text>គណបក្ស</text><bbox><x1>423</x1><y1>39</y1><x2>492</x2><y2>64</y2></bbox></word><word><text>ធម្មាធិបតេយ្យ</text><bbox><x1>492</x1><y1>39</y1><x2>593</x2><y2>64</y2></bbox></word><word><text> </text><bbox><x1>593</x1><y1>39</y1><x2>600</x2><y2>59</y2></bbox></word><word><text>ទី៥</text><bbox><x1>10</x1><y1>68</y1><x2>37</x2><y2>88</y2></bbox></word><word><text> </text><bbox><x1>37</x1><y1>68</y1><x2>44</x2><y2>88</y2></bbox></word><word><text>គណបក្ស</text><bbox><x1>44</x1><y1>68</y1><x2>113</x2><y2>93</y2></bbox></word><word><text>កម្លាំង</text><bbox><x1>113</x1><y1>68</y1><x2>157</x2><y2>93</y2></bbox></word><word><text>ប្រជាធិបតេយ្យ</text><bbox><x1>157</x1><y1>68</y1><x2>264</x2><y2>93</y2></bbox></word><word><text> </text><bbox><x1>264</x1><y1>68</y1><x2>271</x2><y2>88</y2></bbox></word><word><text>ទី៦</text><bbox><x1>271</x1><y1>68</y1><x2>298</x2><y2>88</y2></bbox></word><word><text> </text><bbox><x1>298</x1><y1>68</y1><x2>305</x2><y2>88</y2></bbox></word><word><text>គណបក្ស</text><bbox><x1>305</x1><y1>68</y1><x2>374</x2><y2>93</y2></bbox></word><word><text>សញ្ជាតិ</text><bbox><x1>374</x1><y1>68</y1><x2>431</x2><y2>93</y2></bbox></word><word><text>កម្ពុជា</text><bbox><x1>431</x1><y1>68</y1><x2>475</x2><y2>97</y2></bbox></word><word><text> </text><bbox><x1>475</x1><y1>68</y1><x2>482</x2><y2>88</y2></bbox></word><word><text>ទី៧</text><bbox><x1>482</x1><y1>68</y1><x2>511</x2><y2>88</y2></bbox></word><word><text> </text><bbox><x1>511</x1><y1>68</y1><x2>518</x2><y2>88</y2></bbox></word><word><text>គណបក្ស</text><bbox><x1>518</x1><y1>68</y1><x2>587</x2><y2>93</y2></bbox></word><word><text>ខ្មែរ</text><bbox><x1>587</x1><y1>68</y1><x2>612</x2><y2>93</y2></bbox></word><word><text>តែ</text><bbox><x1>10</x1><y1>97</y1><x2>29</x2><y2>117</y2></bbox></word><word><text>មួយ</text><bbox><x1>29</x1><y1>97</y1><x2>61</x2><y2>124</y2></bbox></word><word><text> </text><bbox><x1>61</x1><y1>97</y1><x2>68</x2><y2>117</y2></bbox></word><word><text>និង</text><bbox><x1>68</x1><y1>97</y1><x2>93</x2><y2>117</y2></bbox></word><word><text>ទី៨</text><bbox><x1>93</x1><y1>97</y1><x2>120</x2><y2>117</y2></bbox></word><word><text> </text><bbox><x1>120</x1><y1>97</y1><x2>127</x2><y2>117</y2></bbox></word><word><text>គណបក្ស</text><bbox><x1>127</x1><y1>97</y1><x2>196</x2><y2>122</y2></bbox></word><word><text>ខ្មែរ</text><bbox><x1>196</x1><y1>97</y1><x2>221</x2><y2>122</y2></bbox></word><word><text>អភិរក្ស</text><bbox><x1>221</x1><y1>97</y1><x2>271</x2><y2>122</y2></bbox></word><word><text> </text><bbox><x1>271</x1><y1>97</y1><x2>278</x2><y2>117</y2></bbox></word><word><text>ការចុះបញ្ជី</text><bbox><x1>278</x1><y1>97</y1><x2>356</x2><y2>124</y2></bbox></word><word><text>គណបក្ស</text><bbox><x1>356</x1><y1>97</y1><x2>425</x2><y2>122</y2></bbox></word><word><text>នយោបាយ</text><bbox><x1>425</x1><y1>97</y1><x2>507</x2><y2>118</y2></bbox></word><word><text>ឈរឈ្មោះ</text><bbox><x1>507</x1><y1>97</y1><x2>583</x2><y2>122</y2></bbox></word><word><text>បោះឆ្នោត</text><bbox><x1>10</x1><y1>126</y1><x2>82</x2><y2>151</y2></bbox></word><word><text> </text><bbox><x1>82</x1><y1>126</y1><x2>89</x2><y2>146</y2></bbox></word><word><text>និង</text><bbox><x1>89</x1><y1>126</y1><x2>114</x2><y2>146</y2></bbox></word><word><text>បញ្ជី</text><bbox><x1>114</x1><y1>126</y1><x2>146</x2><y2>151</y2></bbox></word><word><text>បេក្ខជន</text><bbox><x1>146</x1><y1>126</y1><x2>203</x2><y2>151</y2></bbox></word><word><text>ឈរឈ្មោះ</text><bbox><x1>203</x1><y1>126</y1><x2>279</x2><y2>151</y2></bbox></word><word><text> </text><bbox><x1>279</x1><y1>126</y1><x2>286</x2><y2>146</y2></bbox></word><word><text>សម្រាប់</text><bbox><x1>286</x1><y1>126</y1><x2>343</x2><y2>151</y2></bbox></word><word><text>ការបោះឆ្នោត</text><bbox><x1>343</x1><y1>126</y1><x2>440</x2><y2>151</y2></bbox></word><word><text>ជ្រើសតាំង</text><bbox><x1>440</x1><y1>126</y1><x2>515</x2><y2>151</y2></bbox></word><word><text>តំណាងរាស្រ្ត</text><bbox><x1>515</x1><y1>126</y1><x2>608</x2><y2>151</y2></bbox></word><word><text> </text><bbox><x1>10</x1><y1>155</y1><x2>17</x2><y2>175</y2></bbox></word><word><text>នីតិកាល</text><bbox><x1>17</x1><y1>155</y1><x2>81</x2><y2>175</y2></bbox></word><word><text>ទី៧</text><bbox><x1>81</x1><y1>155</y1><x2>110</x2><y2>175</y2></bbox></word><word><text> </text><bbox><x1>110</x1><y1>155</y1><x2>117</x2><y2>175</y2></bbox></word><word><text>ឆ្នាំ</text><bbox><x1>117</x1><y1>155</y1><x2>136</x2><y2>180</y2></bbox></word><word><text>២០២៣</text><bbox><x1>136</x1><y1>155</y1><x2>198</x2><y2>175</y2></bbox></word><word><text> </text><bbox><x1>198</x1><y1>155</y1><x2>205</x2><y2>175</y2></bbox></word><word><text>មាន</text><bbox><x1>205</x1><y1>155</y1><x2>237</x2><y2>175</y2></bbox></word><word><text>រយៈពេល</text><bbox><x1>237</x1><y1>155</y1><x2>306</x2><y2>175</y2></bbox></word><word><text> </text><bbox><x1>306</x1><y1>155</y1><x2>313</x2><y2>175</y2></bbox></word><word><text>១៥</text><bbox><x1>313</x1><y1>155</y1><x2>342</x2><y2>175</y2></bbox></word><word><text> </text><bbox><x1>342</x1><y1>155</y1><x2>349</x2><y2>175</y2></bbox></word><word><text>ថ្ងៃ</text><bbox><x1>349</x1><y1>155</y1><x2>369</x2><y2>180</y2></bbox></word><word><text> </text><bbox><x1>369</x1><y1>155</y1><x2>376</x2><y2>175</y2></bbox></word><word><text>គឺ</text><bbox><x1>376</x1><y1>155</y1><x2>389</x2><y2>175</y2></bbox></word><word><text>ចាប់ពី</text><bbox><x1>389</x1><y1>155</y1><x2>433</x2><y2>175</y2></bbox></word><word><text>ថ្ងៃទី</text><bbox><x1>433</x1><y1>155</y1><x2>465</x2><y2>180</y2></bbox></word><word><text>២៤</text><bbox><x1>465</x1><y1>155</y1><x2>494</x2><y2>175</y2></bbox></word><word><text> </text><bbox><x1>494</x1><y1>155</y1><x2>501</x2><y2>175</y2></bbox></word><word><text>ខែមេសា</text><bbox><x1>501</x1><y1>155</y1><x2>564</x2><y2>175</y2></bbox></word><word><text> </text><bbox><x1>564</x1><y1>155</y1><x2>571</x2><y2>175</y2></bbox></word><word><text>រហូតដល់</text><bbox><x1>10</x1><y1>184</y1><x2>79</x2><y2>210</y2></bbox></word><word><text>ថ្ងៃទី</text><bbox><x1>79</x1><y1>184</y1><x2>111</x2><y2>209</y2></bbox></word><word><text>៨</text><bbox><x1>111</x1><y1>184</y1><x2>125</x2><y2>204</y2></bbox></word><word><text> </text><bbox><x1>125</x1><y1>184</y1><x2>132</x2><y2>204</y2></bbox></word><word><text>ខែឧសភា</text><bbox><x1>132</x1><y1>184</y1><x2>201</x2><y2>205</y2></bbox></word></metadata>