<?xml version='1.0' encoding='utf-8'?>
<metadata><image>kh_data_323.png</image><width>628</width><height>380</height><word><text>ក្អួត</text><bbox><x1>10</x1><y1>10</y1><x2>41</x2><y2>46</y2></bbox></word><word><text> </text><bbox><x1>41</x1><y1>10</y1><x2>47</x2><y2>31</y2></bbox></word><word><text>រាក</text><bbox><x1>47</x1><y1>10</y1><x2>77</x2><y2>31</y2></bbox></word><word><text> </text><bbox><x1>77</x1><y1>10</y1><x2>83</x2><y2>31</y2></bbox></word><word><text>ពិបាក</text><bbox><x1>83</x1><y1>10</y1><x2>133</x2><y2>32</y2></bbox></word><word><text>នោម</text><bbox><x1>133</x1><y1>10</y1><x2>177</x2><y2>31</y2></bbox></word><word><text> </text><bbox><x1>177</x1><y1>10</y1><x2>183</x2><y2>31</y2></bbox></word><word><text>ឈឺ</text><bbox><x1>183</x1><y1>10</y1><x2>212</x2><y2>31</y2></bbox></word><word><text>ក្បាល</text><bbox><x1>212</x1><y1>10</y1><x2>261</x2><y2>39</y2></bbox></word><word><text> </text><bbox><x1>261</x1><y1>10</y1><x2>267</x2><y2>31</y2></bbox></word><word><text>ស្ថានភាព</text><bbox><x1>267</x1><y1>10</y1><x2>343</x2><y2>39</y2></bbox></word><word><text>ផ្លូវចិត្ត</text><bbox><x1>343</x1><y1>10</y1><x2>402</x2><y2>46</y2></bbox></word><word><text>ប្រែប្រួល</text><bbox><x1>402</x1><y1>10</y1><x2>475</x2><y2>45</y2></bbox></word><word><text> </text><bbox><x1>475</x1><y1>10</y1><x2>481</x2><y2>31</y2></bbox></word><word><text>និង</text><bbox><x1>481</x1><y1>10</y1><x2>510</x2><y2>31</y2></bbox></word><word><text>វិបត្តិ</text><bbox><x1>510</x1><y1>10</y1><x2>556</x2><y2>39</y2></bbox></word><word><text>តម្រងនោម</text><bbox><x1>10</x1><y1>46</y1><x2>105</x2><y2>75</y2></bbox></word><word><text>ស្រួច</text><bbox><x1>105</x1><y1>46</y1><x2>147</x2><y2>81</y2></bbox></word><word><text>ស្រាល់</text><bbox><x1>147</x1><y1>46</y1><x2>202</x2><y2>75</y2></bbox></word><word><text>ដែល</text><bbox><x1>202</x1><y1>46</y1><x2>244</x2><y2>67</y2></bbox></word><word><text>អាច</text><bbox><x1>244</x1><y1>46</y1><x2>281</x2><y2>67</y2></bbox></word><word><text>បង្កឲ្យ</text><bbox><x1>281</x1><y1>46</y1><x2>335</x2><y2>75</y2></bbox></word><word><text>ស្លាប់</text><bbox><x1>335</x1><y1>46</y1><x2>376</x2><y2>75</y2></bbox></word><word><text>បាន</text><bbox><x1>376</x1><y1>46</y1><x2>411</x2><y2>68</y2></bbox></word><word><text>។</text><bbox><x1>411</x1><y1>46</y1><x2>425</x2><y2>67</y2></bbox></word><word><text> </text><bbox><x1>425</x1><y1>46</y1><x2>431</x2><y2>67</y2></bbox></word><word><text>ក្រុមប្រឹក្សា</text><bbox><x1>431</x1><y1>46</y1><x2>520</x2><y2>80</y2></bbox></word><word><text>ធុរកិច្ច</text><bbox><x1>520</x1><y1>46</y1><x2>572</x2><y2>75</y2></bbox></word><word><text>អាមេរិក</text><bbox><x1>10</x1><y1>82</y1><x2>78</x2><y2>103</y2></bbox></word><word><text>-</text><bbox><x1>78</x1><y1>82</y1><x2>85</x2><y2>103</y2></bbox></word><word><text>តៃវ៉ាន់</text><bbox><x1>85</x1><y1>82</y1><x2>143</x2><y2>103</y2></bbox></word><word><text> </text><bbox><x1>143</x1><y1>82</y1><x2>149</x2><y2>103</y2></bbox></word><word><text>រួម</text><bbox><x1>149</x1><y1>82</y1><x2>173</x2><y2>111</y2></bbox></word><word><text>ជាមួយ</text><bbox><x1>173</x1><y1>82</y1><x2>231</x2><y2>111</y2></bbox></word><word><text>ក្រុមប្រឹក្សា</text><bbox><x1>231</x1><y1>82</y1><x2>320</x2><y2>116</y2></bbox></word><word><text>អភិវឌ្ឍ</text><bbox><x1>320</x1><y1>82</y1><x2>385</x2><y2>111</y2></bbox></word><word><text>ពាណិជ្ជកម្ម</text><bbox><x1>385</x1><y1>82</y1><x2>476</x2><y2>111</y2></bbox></word><word><text>ក្រៅ</text><bbox><x1>476</x1><y1>82</y1><x2>514</x2><y2>111</y2></bbox></word><word><text>ស្រុក</text><bbox><x1>514</x1><y1>82</y1><x2>557</x2><y2>116</y2></bbox></word><word><text>តៃវ៉ាន់</text><bbox><x1>557</x1><y1>82</y1><x2>615</x2><y2>103</y2></bbox></word><word><text> </text><bbox><x1>615</x1><y1>82</y1><x2>621</x2><y2>103</y2></bbox></word><word><text>នឹង</text><bbox><x1>10</x1><y1>118</y1><x2>39</x2><y2>139</y2></bbox></word><word><text>រៀបចំ</text><bbox><x1>39</x1><y1>118</y1><x2>92</x2><y2>147</y2></bbox></word><word><text>វេទិកា</text><bbox><x1>92</x1><y1>118</y1><x2>150</x2><y2>139</y2></bbox></word><word><text>ឧស្សាហកម្ម</text><bbox><x1>150</x1><y1>118</y1><x2>247</x2><y2>147</y2></bbox></word><word><text>ការពារ</text><bbox><x1>247</x1><y1>118</y1><x2>306</x2><y2>139</y2></bbox></word><word><text>ជាតិ</text><bbox><x1>306</x1><y1>118</y1><x2>342</x2><y2>139</y2></bbox></word><word><text>តៃវ៉ាន់</text><bbox><x1>342</x1><y1>118</y1><x2>400</x2><y2>139</y2></bbox></word><word><text>-</text><bbox><x1>400</x1><y1>118</y1><x2>407</x2><y2>139</y2></bbox></word><word><text>អាមេរិក</text><bbox><x1>407</x1><y1>118</y1><x2>475</x2><y2>139</y2></bbox></word><word><text> </text><bbox><x1>475</x1><y1>118</y1><x2>481</x2><y2>139</y2></bbox></word><word><text>នៅ</text><bbox><x1>481</x1><y1>118</y1><x2>511</x2><y2>139</y2></bbox></word><word><text>ទីក្រុង</text><bbox><x1>511</x1><y1>118</y1><x2>563</x2><y2>152</y2></bbox></word><word><text>តៃ</text><bbox><x1>563</x1><y1>118</y1><x2>587</x2><y2>139</y2></bbox></word><word><text>ប៉ិ</text><bbox><x1>587</x1><y1>118</y1><x2>602</x2><y2>147</y2></bbox></word><word><text> </text><bbox><x1>602</x1><y1>118</y1><x2>608</x2><y2>139</y2></bbox></word><word><text>នា</text><bbox><x1>10</x1><y1>154</y1><x2>31</x2><y2>175</y2></bbox></word><word><text>ថ្ងៃពុធ</text><bbox><x1>31</x1><y1>154</y1><x2>82</x2><y2>183</y2></bbox></word><word><text>សប្តាហ៍</text><bbox><x1>82</x1><y1>154</y1><x2>143</x2><y2>183</y2></bbox></word><word><text>នេះ</text><bbox><x1>143</x1><y1>154</y1><x2>173</x2><y2>175</y2></bbox></word><word><text> </text><bbox><x1>173</x1><y1>154</y1><x2>179</x2><y2>175</y2></bbox></word><word><text>ដែល</text><bbox><x1>179</x1><y1>154</y1><x2>221</x2><y2>175</y2></bbox></word><word><text>នឹង</text><bbox><x1>221</x1><y1>154</y1><x2>250</x2><y2>175</y2></bbox></word><word><text>ប្រមូលផ្តុំ</text><bbox><x1>250</x1><y1>154</y1><x2>321</x2><y2>190</y2></bbox></word><word><text>ក្រុមហ៊ុន</text><bbox><x1>321</x1><y1>154</y1><x2>393</x2><y2>188</y2></bbox></word><word><text>របស់</text><bbox><x1>393</x1><y1>154</y1><x2>436</x2><y2>175</y2></bbox></word><word><text>តៃវ៉ាន់</text><bbox><x1>436</x1><y1>154</y1><x2>494</x2><y2>175</y2></bbox></word><word><text>និង</text><bbox><x1>494</x1><y1>154</y1><x2>523</x2><y2>175</y2></bbox></word><word><text>អាមេរិក</text><bbox><x1>523</x1><y1>154</y1><x2>591</x2><y2>175</y2></bbox></word><word><text> </text><bbox><x1>591</x1><y1>154</y1><x2>597</x2><y2>175</y2></bbox></word><word><text>ដើម្បី</text><bbox><x1>10</x1><y1>190</y1><x2>55</x2><y2>219</y2></bbox></word><word><text>ពិភាក្សា</text><bbox><x1>55</x1><y1>190</y1><x2>120</x2><y2>219</y2></bbox></word><word><text>គ្នា</text><bbox><x1>120</x1><y1>190</y1><x2>142</x2><y2>219</y2></bbox></word><word><text>អំពី</text><bbox><x1>142</x1><y1>190</y1><x2>170</x2><y2>211</y2></bbox></word><word><text>កិច្ចសហប្រតិបត្តិការ</text><bbox><x1>170</x1><y1>190</y1><x2>336</x2><y2>219</y2></bbox></word><word><text>។</text><bbox><x1>336</x1><y1>190</y1><x2>350</x2><y2>211</y2></bbox></word><word><text> </text><bbox><x1>350</x1><y1>190</y1><x2>356</x2><y2>211</y2></bbox></word><word><text>សហរដ្ឋ</text><bbox><x1>356</x1><y1>190</y1><x2>418</x2><y2>219</y2></bbox></word><word><text>អាមេរិក</text><bbox><x1>418</x1><y1>190</y1><x2>486</x2><y2>211</y2></bbox></word><word><text>គឺជា</text><bbox><x1>486</x1><y1>190</y1><x2>521</x2><y2>211</y2></bbox></word><word><text>អ្នកផ្គត់ផ្គង់</text><bbox><x1>521</x1><y1>190</y1><x2>608</x2><y2>219</y2></bbox></word><word><text>សព្វាវុធ</text><bbox><x1>10</x1><y1>226</y1><x2>80</x2><y2>255</y2></bbox></word><word><text>ធំ</text><bbox><x1>80</x1><y1>226</y1><x2>95</x2><y2>247</y2></bbox></word><word><text>បំផុត</text><bbox><x1>95</x1><y1>226</y1><x2>140</x2><y2>255</y2></bbox></word><word><text>របស់</text><bbox><x1>140</x1><y1>226</y1><x2>183</x2><y2>247</y2></bbox></word><word><text>តៃវ៉ាន់</text><bbox><x1>183</x1><y1>226</y1><x2>241</x2><y2>247</y2></bbox></word><word><text> </text><bbox><x1>241</x1><y1>226</y1><x2>247</x2><y2>247</y2></bbox></word><word><text>ទោះ</text><bbox><x1>247</x1><y1>226</y1><x2>284</x2><y2>247</y2></bbox></word><word><text>មិន</text><bbox><x1>284</x1><y1>226</y1><x2>313</x2><y2>247</y2></bbox></word><word><text>មាន</text><bbox><x1>313</x1><y1>226</y1><x2>349</x2><y2>247</y2></bbox></word><word><text>ទំនាក់ទំនង</text><bbox><x1>349</x1><y1>226</y1><x2>443</x2><y2>247</y2></bbox></word><word><text>ផ្លូវការ</text><bbox><x1>443</x1><y1>226</y1><x2>502</x2><y2>262</y2></bbox></word><word><text>ជាមួយគ្នា</text><bbox><x1>502</x1><y1>226</y1><x2>581</x2><y2>255</y2></bbox></word><word><text>ក៏ដោយ</text><bbox><x1>10</x1><y1>262</y1><x2>76</x2><y2>283</y2></bbox></word><word><text> </text><bbox><x1>76</x1><y1>262</y1><x2>82</x2><y2>283</y2></bbox></word><word><text>ហើយ</text><bbox><x1>82</x1><y1>262</y1><x2>133</x2><y2>283</y2></bbox></word><word><text>ប្រធានបទ</text><bbox><x1>133</x1><y1>262</y1><x2>220</x2><y2>291</y2></bbox></word><word><text>ពាក់ព័ន្ធ</text><bbox><x1>220</x1><y1>262</y1><x2>285</x2><y2>291</y2></bbox></word><word><text>ដែន</text><bbox><x1>285</x1><y1>262</y1><x2>321</x2><y2>283</y2></bbox></word><word><text>កោះ</text><bbox><x1>321</x1><y1>262</y1><x2>358</x2><y2>283</y2></bbox></word></metadata>